[
    {
        "id": 775,
        "title": "Bản tin Năng lượng Quốc tế 27/2: Giới chức Mỹ nói giới hạn giá dầu Nga đang phát huy tác dụng",
        "url": "https://www.pvoil.com.vn/ban-tin-nang-luong-quoc-te-272-gioi-chuc-my-noi-gioi-han-gia-dau-nga-dang-phat-huy-tac-dung",
        "ngay_crawl": "2025-09-09 16:44:02"
    },
    {
        "id": 776,
        "title": "Giá dầu thô tăng nhẹ nhờ lo ngại thiếu hụt nguồn cung",
        "url": "https://www.pvoil.com.vn/gia-dau-tho-tang-nhe-nho-lo-ngai-thieu-hut-nguon-cung",
        "ngay_crawl": "2025-09-09 16:44:02"
    },
    {
        "id": 777,
        "title": "Nhịp đập thị trường năng lượng ngày 26/2/2023",
        "url": "https://www.pvoil.com.vn/nhip-dap-thi-truong-nang-luong-ngay-2622023",
        "ngay_crawl": "2025-09-09 16:44:02"
    },
    {
        "id": 778,
        "title": "Giá dầu thế giới chốt phiên 23/2 tăng 2%",
        "url": "https://www.pvoil.com.vn/gia-dau-the-gioi-chot-phien-232-tang-2",
        "ngay_crawl": "2025-09-09 16:44:02"
    },
    {
        "id": 779,
        "title": "Tiềm năng và cơ hội tích hợp hydrogen",
        "url": "https://www.pvoil.com.vn/tiem-nang-va-co-hoi-tich-hop-hydrogen-sach-vao-che-bien-dau-khi-cua-petrovietnam",
        "ngay_crawl": "2025-09-09 16:44:02"
    },
    {
        "id": 780,
        "title": "Nhịp đập thị trường năng lượng ngày 22/2/2023",
        "url": "https://www.pvoil.com.vn/nhip-dap-thi-truong-nang-luong-ngay-2222023",
        "ngay_crawl": "2025-09-09 16:44:02"
    },
    {
        "id": 781,
        "title": "Giá dầu thế giới thay đổi ít trong phiên sáng 22/2",
        "url": "https://www.pvoil.com.vn/gia-dau-the-gioi-thay-doi-it-trong-phien-sang-222",
        "ngay_crawl": "2025-09-09 16:44:02"
    },
    {
        "id": 782,
        "title": "Bản tin Năng lượng Quốc tế 21/2: Nhu cầu dầu toàn cầu cao kỷ lục trong tháng 12",
        "url": "https://www.pvoil.com.vn/ban-tin-nang-luong-quoc-te-212-nhu-cau-dau-toan-cau-cao-ky-luc-trong-thang-12",
        "ngay_crawl": "2025-09-09 16:44:02"
    },
    {
        "id": 783,
        "title": "Giá dầu Brent giảm hơn 1% trong phiên 21/2",
        "url": "https://www.pvoil.com.vn/gia-dau-brent-giam-hon-1-trong-phien-212",
        "ngay_crawl": "2025-09-09 16:44:02"
    }
]