[
    {
        "id": 36,
        "title": "Đảng bộ PV Power tổ chức Hội nghị Ban Chấp hành mở rộng lần thứ 16",
        "url": "https://pvpower.vn/vi/post/dang-bo-pv-power-to-chuc-hoi-nghi-ban-chap-hanh-mo-rong-lan-thu-16-5901.htm",
        "ngay_crawl": "2025-09-09 14:46:23"
    },
    {
        "id": 37,
        "title": "“Xuân nghĩa tình dầu khí – Tết ấm áp sẻ chia\" tại Nhiệt điện Vũng Áng 1",
        "url": "https://pvpower.vn/vi/post/xuan-nghia-tinh-dau-khi---tet-am-ap-se-chia--tai-nhiet-dien-vung-ang-1-5898.htm",
        "ngay_crawl": "2025-09-09 14:46:23"
    },
    {
        "id": 38,
        "title": "Thủ tướng Chính phủ cùng Thủ tướng Lào chủ trì Hội nghị hợp tác đầu tư Việt - Lào",
        "url": "https://pvpower.vn/vi/post/thu-tuong--chinh-phu-cung-thu-tuong-lao--chu-tri-hoi-nghi-hop-tac-dau-tu-viet-lao-5885.htm",
        "ngay_crawl": "2025-09-09 14:46:23"
    },
    {
        "id": 39,
        "title": "Bí thư Tỉnh ủy Nguyễn Hồng Lĩnh kiểm tra các dự án nhiệt điện Nhơn Trạch 3, Nhơn Trạch 4 và cảng Phước An",
        "url": "https://pvpower.vn/vi/post/bi-thu-tinh-uy-nguyen-hong-linh-kiem-tra-cac-du-an-nhiet-dien-nhon-trach-3--nhon-trach-4-va-cang-phuoc-an-5857.htm",
        "ngay_crawl": "2025-09-09 14:46:23"
    },
    {
        "id": 40,
        "title": "Đẩy nhanh tiến độ dự án nhiệt điện LNG 1,4 tỷ USD",
        "url": "https://pvpower.vn/vi/post/day-nhanh-tien-do-du-an-nhiet-dien-lng-1-4-ty-usd-5828.htm",
        "ngay_crawl": "2025-09-09 14:46:23"
    },
    {
        "id": 41,
        "title": "Chuyện hồi sinh Tổ máy số 1 NMNĐ Vũng Áng 1",
        "url": "https://pvpower.vn/vi/post/chuyen-hoi-sinh-to-may-so-1-nmnd-vung-ang-1-5826.htm",
        "ngay_crawl": "2025-09-09 14:46:23"
    },
    {
        "id": 42,
        "title": "Siêu dự án điện 1,4 tỷ USD ở Đồng Nai",
        "url": "https://pvpower.vn/vi/post/sieu-du-an-dien-1-4-ty-usd-o-dong-nai-5823.htm",
        "ngay_crawl": "2025-09-09 14:46:23"
    }
]