[
    {
        "id": 1999,
        "title": "TT năng lượng TG ngày 30/9/2020: Giá dầu và khí tự nhiên giảm",
        "url": "https://www.pvoil.com.vn/tt-nang-luong-tg-ngay-3092020-gia-dau-va-khi-tu-nhien-giam",
        "content": "Giá dầu thế giới ngày 30/9 giảm sau khi giảm phiên trước đó, trong bối cảnh lo ngại về nhu cầu nhiên liệu giảm do đại dịch COVID-19 ngày càng trở nên tồi tệ hơn. Giá dầu thế giới ngày 30/9 giảm sau khi giảm phiên trước đó,  trong bối cảnh lo ngại về nhu cầu nhiên liệu giảm do đại dịch COVID-19 ngày càng trở nên tồi tệ hơn. Giá dầu Brent giảm 23 US cent tương đương 0,6% xuống 41,03 USD/thùng. Giá dầu thô Mỹ (WTI) giảm 26 US cent tương đương 0,7% xuống 39,29 USD/thùng. Giám đốc điều hành các công ty thương mại lớn nhất thế giới dự báo nhu cầu dầu phục hồi yếu và ít biến động về giá trong những tháng tới và trong nhiều năm tới. Nhu cầu  nhiên liệu máy bay chịu áp lực giảm, do việc đi lại bằng đường hàng không giảm bởi đại dịch COVID-19. Marathon Petroleum Corp MPC.N - công ty lọc dầu lớn nhất tại Mỹ bắt đầu áp dụng việc cắt giảm việc làm vào thứ ba (29/9). Để ngăn chặn sự sụt giảm nhu cầu, Tổ chức Các nước Xuất khẩu Dầu mỏ dự kiến cắt giảm sản lượng dầu theo kế hoạch từ tháng 1/2021. Marathon Petroleum Corp MPC.N, công ty lọc dầu lớn nhất tại Mỹ bắt đầu áp dụng việc cắt giảm việc làm vào thứ ba (29/9) Số liệu từ Viện Dầu mỏ Mỹ cho biết,  tồn trữ dầu thô của Mỹ giảm so với kỳ vọng, thay vào đó tập trung vào gia tăng tồn trữ xăng. Giá khí tự nhiên giảm hơn 8% do nhu cầu thấp, sản lượng tăng Giá khí tự nhiên tại Mỹ giảm hơn 8% trong ngày thứ ba (29/9/2020),  do dự báo nhu cầu trong hai tuần tới thấp hơn so với dự kiến trước đó và sản lượng tăng. Giá khí tự nhiên kỳ hạn tháng 11/2020 giảm 23,4 US cent tương đương 8,4% xuống 2,561 USD/mmBtu, song vẫn ở mức cao nhất kể từ ngày 4/9. Nhà cung cấp dữ liệu Refinitiv cho biết, sản lượng tại 48 tiểu bang của Mỹ  tăng lên mức cao nhất trong một tuần là 86,1 tỷ feet khối mỗi ngày (bcfd) vào thứ hai (28/9) từ mức thấp nhất trong 4 tháng là 84,4 bcfd trong tuần trước.\nMặt hàng\nĐơn vị tính\nGiá hiện nay\n+/-\nThay đổi so với 1 ngày trước\nThay đổi so với 1 năm trước\nDầu WTI\nUSD/thùng\n38,8700\n0,42\n-1,07\n-27,66\nDầu Brent\nUSD/thùng\n40,4500\n0,58\n-3,38\n-31,47\nKhí tự nhiên\nUSD/mmBtu\n2,4880\n0,027\n13,86\n9,02\nXăng\nUSD/gallon\n1,1736\n0,015\n0,43\n-25,53\nDầu đốt\nUSD/gallon\n1,1044\n0,002\n0,68\n-41,93\nThan đá\nUSD/tấn\n61,00\n0,00\n0,00\n0,00\nNguồn : VITIC/Reuters",
        "ngay_dang": "01.10.2020",
        "ngay_crawl": "2025-09-10 07:27:50"
    },
    {
        "id": 2000,
        "title": "Giá dầu thế giới giảm hơn 3%, xuống mức thấp nhất trong hai tuần",
        "url": "https://www.pvoil.com.vn/gia-dau-the-gioi-giam-hon-3-xuong-muc-thap-nhat-trong-hai-tuan",
        "content": "Giá dầu thế giới giảm hơn 3% trong phiên 29/9 xuống mức thấp nhất trong hai tuần do lo ngại về triển vọng nhu cầu nhiên liệu khi châu Âu và Mỹ đối mặt với sự gia tăng số ca mắc COVID-19.\nBể chứa dầu tại Carson, California, Mỹ. (Ảnh: AFP/TTXVN)\nGiá dầu thế giới giảm hơn 3% trong phiên giao dịch 29/9 xuống mức thấp nhất trong hai tuần do lo ngại về triển vọng nhu cầu nhiên liệu khi châu Âu và Mỹ đối mặt với sự gia tăng số ca mắc dịch viêm đường hô hấp cấp COVID-19 mới. Trong phiên giao dịch này, giá dầu Brent giao tháng 11/2020 tại thị trường London (Vương quốc Anh) giảm 1,40 USD (3,3%) xuống 41,03 USD/thùng. Trong khi đó, giá dầu Brent giao tháng 12/2020 giảm 3,1% xuống 41,56 USD/thùng. Còn giá dầu thô ngọt nhẹ Mỹ (WTI) tại thị trường New York (Mỹ) cũng giảm 1,31 USD (3,2%) xuống 39,29 USD/thùng. Theo số liệu thống kê của hãng tin Reuters, hơn một triệu người trên toàn thế giới đã chết vì COVID-19, một cột mốc ảm đạm của đại dịch đã tàn phá nền kinh tế toàn cầu và làm sụt giảm nhu cầu nhiên liệu. Craig Erlam, nhà phân tích cao cấp của trung tâm OANDA cho biết tình hình dịch COVID-19 đang bùng phát trở lại khiến giá dầu thô sụt giảm mạnh. Nhu cầu dầu mỏ dự kiến sẽ phục hồi chậm và giá \"vàng đen\" sẽ đi ngang trong những tháng tới và thậm chí có thể trong nhiều năm./. Nguồn tin: vietnamplus",
        "ngay_dang": "30.09.2020",
        "ngay_crawl": "2025-09-10 07:27:50"
    },
    {
        "id": 2001,
        "title": "TT năng lượng TG ngày 29/9/2020: Giá dầu và khí tự nhiên giảm",
        "url": "https://www.pvoil.com.vn/tt-nang-luong-tg-ngay-2992020-gia-dau-va-khi-tu-nhien-giam",
        "content": "Giá dầu thế giới ngày 29/9 giảm do lo ngại về nhu cầu nhiên liệu giảm khi số trường hợp nhiễm virus corona tăng, làm gia tăng kỳ vọng rằng các nhà lập pháp Mỹ và Nhà Trắng sắp đạt được thỏa thuận về gói kích thích mới để vực dậy nền kinh tế lớn nhất thế giới. Giá dầu thô MỸ (WTI) giảm 17 US cent tương đương 0,4% xuống 40,43 USD/thùng. Giá dầu Brent cũng giảm 17 US cent tương đương 0,4% xuống 42,26 USD/thùng. Cả hai loại dầu này tăng khoảng 1%  đóng cửa phiên thứ hai (28/9). Thị trường hàng hóa đã tăng mạnh trong đầu phiên giao dịch,  khi các nhà lập pháp Dân chủ công bố dự luật cứu trợ COVID-19 trị giá 2,2 nghìn tỷ USD mà Chủ tịch Hạ viện Mỹ Nancy Pelosi cho rằng đó là một biện pháp thỏa hiệp. Chiến lược gia thị trường Stephen Innes thuộc AxiCorp cho biết: “Nếu điều đó xảy ra, các biện pháp kích thích của Mỹ sẽ đi một chặng đường dài để thúc đẩy nhu cầu dầu vào thời điểm quan trọng nhất và có thể đưa giá dầu trở  lại như hồi đầu tháng 9/2020”. Cả hai loại dầu Brent và dầu thô (WTI) trong tháng 8/2020 đạt mức cao nhất kể từ đầu tháng 3/2020, do lạc quan về nhu cầu nhiên liệu tăng và việc các nhà sản xuất dầu lớn tuân thủ chặt chẽ cam kết cắt giảm nguồn cung, nhưng sau đó đã giảm khoảng 3 USD do lo ngại về nhu cầu. Nhập khẩu dầu thô trong tháng 8/2020 của Nhật Bản, nước tiêu thụ lớn thứ tư thế giới, giảm gần 26% so với tháng trước. Qua thăm dò 5 nhà phân tích, ước tính tồn kho dầu thô trung bình của Mỹ tăng 1,4 triệu thùng trong tuần tính đến ngày 25/9. Tồn trữ xăng giảm 1,6 triệu thùng và tồn trữ sản phẩm chưng cất, bao gồm dầu diesel và nhiên liệu máy bay giảm 800.000 thùng. Về phía nguồn cung, các thương nhân để mắt đến các cuộc đụng độ giữa Armenia và Azerbaijan trong khu vực Nagorno-Karabakh. Các nhà phân tích cho biết, nếu xung đột leo thang, điều này có thể ảnh hưởng đến xuất khẩu dầu và khí đốt từ Azerbaijan. Đường ống dẫn dầu chính của Azerbaijan chạy qua Georgia đến bờ biển Địa Trung Hải của Thổ Nhĩ Kỳ. Giá khí tự nhiên giảm khoảng 2% Giá khí tự nhiên tại Mỹ giảm gần 2% trong ngày 28/9, ngày cuối cùng của kỳ hạn tháng 10/2020 do nguồn cung thặng dự và mối đe dọa về cơn bão ở Đại Tây Dương suy yếu. Giá khí tự nhiên giảm, bất chấp  xuất khẩu khí tự nhiên hóa lỏng (LNG) dự kiến tăng. Hợp đồng khí tự nhiên kỳ hạn tháng 10/2020 giảm 3,8 US cent tương đương 1,8% xuống 2,101 USD/mmBtu. Hợp đồng kỳ hạn tháng 11 (bắt đầu từ ngày 29/9) giảm 1,2 US cent tương đương 0,4% xuống 2,795 USD/mmBtu\nMặt hàng\nĐơn vị tính\nGiá hiện nay\n+/-\nThay đổi so với 1 ngày trước\nThay đổi so với 1 năm trước\nDầu WTI\nUSD/thùng\n40,3800\n0,22\n-0,54\n-5,30\nDầu Brent\nUSD/thùng\n42,2500\n0,18\n-0,42\n-6,76\nKhí tự nhiên\nUSD/mmBtu\n2,7570\n0,678\n32,60\n4,28\nXăng\nUSD/gallon\n1,2398\n0,0112\n-0,90\n1,27\nDầu đốt\nUSD/gallon\n1,1359\n0,0048\n-0,42\n-7,26\nThan đá\nUSD/tấn\n60,78\n0,65\n1,08\n-15,21\nNguồn : VITIC/Reuters",
        "ngay_dang": "30.09.2020",
        "ngay_crawl": "2025-09-10 07:27:50"
    },
    {
        "id": 2002,
        "title": "TT năng lượng TG ngày 28/9/2020: Giá dầu và khí tự nhiên giảm do nhu cầu thấp",
        "url": "https://www.pvoil.com.vn/tt-nang-luong-tg-ngay-2892020-gia-dau-va-khi-tu-nhien-giam-do-nhu-cau-thap",
        "content": "Giá dầu thế giới ngày 28/9 giảm, do số trường hợp nhiễm virus corona tăng làm giảm bớt kỳ vọng về phục hồi nhu cầu nhiên liệu, trong đó dầu thô có tháng giảm đầu tiên trong nhiều tháng sau khi giảm mạnh trong tuần trước. Giá dầu Brent giảm 8 US cent tương đương 0,2% xuống 41,48 USD/thùng sau khi giảm 2,9% trong tuần trước. Giá dầu thô Mỹ (WTI) giảm 13 US cent tương đương 0,3% xuống 40,12 USD/thùng, sau khi giảm 2,1% trong tuần trước. Giá dầu Brent có tháng đầu tiên trong 6 tháng, trong khi giá dầu WTI có tháng giảm đầu tiên kể từ tháng 4/2020, trong bối cảnh một số quốc gia tái áp đặt các hạn chế đi lại sau khi các ca nhiễm COVID-19 vẫn đang tăng làm lu mờ triển vọng phục hồi nhu cầu nhiên liệu. Các nhà phân tích của ANZ cho biết, số trường hợp COVID-19 mới đang tăng nhanh ở các bang lớn tại Mỹ, làm dấy lên lo ngại các biện pháp hạn chế đi lại ảnh hướng tới sự phục hồi nhu cầu dầu. Các nước thành viên thuộc Tổ chức Các nước Xuất khẩu Dầu mỏ (OPEC) là Iran và Libya đã tăng lượng dầu xuất khẩu bất chấp nỗ lực của OPEC và các nước liên minh sản xuất dầu hạn chế sản lượng. Tổng thư ký OPEC Mohammad Barkindo cho biết vào chủ nhật (27/9) rằng tồn kho dầu thương mại ở các nước OECD dự kiến sẽ chỉ cao hơn một chút so với mức trung bình 5 năm trong quý I/2021, trước khi giảm xuống dưới mức đó trong thời gian còn lại của năm. Hiệp hội Dầu khí Na Uy (NOG) cho biết, Na Uy - một trong những nhà sản xuất dầu lớn nhất ngoài OPEC, cuộc đình công của công nhân tại nước này có thể diễn ra vào ngày 30/9 đe dọa việc cắt giảm sản lượng 900.000 thùng dầu mỗi ngày của Na Uy. Ngoài ra, một trong những cuộc đụng độ nặng nề nhất giữa Armenia và Azerbaijan kể từ năm 2016 đã nổ ra vào cuối tuần qua, làm dấy lên lo ngại về sự ổn định ở Nam Caucasus - đường vận chuyển dầu và khí đốt đến các thị trường thế giới. Giá khí tự nhiên giảm do dự báo nhu cầu thấp Giá khí tự nhiên tại Mỹ có tuần tính đến ngày 25/9/2020 giảm gần 5%,  do giá giao ngay tiếp tục thấp hơn nhiều so với giá kỳ hạn bởi dự báo nhu cầu trong 2 tuần tới thấp hơn so với dự báo trước đó. Giá kỳ hạn giảm bất chấp việc xuất khẩu LNG dự kiến tăng, doanh số bán sang Mexico đạt mức cao kỷ lục và sản lượng hàng ngày giảm xuống mức thấp nhất trong 25 tháng. Hợp đồng khí tự nhiên kỳ hạn tháng 10/2020 giảm 10,9 US cent tương đương 4,8% xuống 2,139 USD/mmBtu. Hợp đồng tháng 11/2020 giảm 9 US cent xuống 2,810 USD/mmBtu. Nếu tháng 11/2020 tiếp tục giao dịch ở mức đó vào tuần tới, sẽ khiến giá đóng cửa tháng 10/2020 lên mức cao nhất kể từ tháng 11/2019. Tính chung trong cả tuần, giá khí tự nhiên tăng khoảng 4% sau khi giảm hơn 10% vào thứ hai (21/9) và tăng gần 16% vào thứ tư (23/9).\nBảng giá năng lượng thế giới 28/9/2020\nMặt hàng\nĐơn vị tính\nGiá hiện nay\n+/-\nThay đổi so với 1 ngày trước\nThay đổi so với 1 năm trước\nDầu WTI\nUSD/thùng\n39,9100\n0,34\n-0,84\n-28,79\nDầu Brent\nUSD/thùng\n41,6300\n0,29\n-0,69\n-32,86\nKhí tự nhiên\nUSD/mmBtu\n2,1200\n0,00\n-0,19\n-9,01\nXăng\nUSD/gallon\n1,2091\n0,0046\n-0,38\n-24,57\nDầu đốt\nUSD/gallon\n1,1215\n0,0034\n-0,30\n-41,06\nThan đá\nUSD/tấn\n60,13\n1,02\n-1,67\n-16,11\nNguồn : VITIC/Reuters",
        "ngay_dang": "29.09.2020",
        "ngay_crawl": "2025-09-10 07:27:51"
    },
    {
        "id": 2003,
        "title": "EIA dự báo lạc quan về thị trường nhiên liệu từ cuối 2020",
        "url": "https://www.pvoil.com.vn/eia-du-bao-lac-quan-ve-thi-truong-nhien-lieu-tu-cuoi-2020",
        "content": "EIA ước tính mức tiêu thụ nhiên liệu toàn cầu tháng 8 trung bình đạt 94,3 triệu bpd, tăng 1,2 triệu bpd so với tháng 7 và 9,2 triệu bpd so với quý 2/2020, tuy nhiên vẫn thấp hơn 8,2 triệu bpd so với cùng kỳ năm 2019.\nMức tiêu thụ bình quân cả năm 2020 dự báo ở mức 93,1 triệu bpd, giảm 8,3 triệu bpd so với năm 2019, sau đó sẽ tăng 6,5 triệu bpd, lên 99,6 triệu bpd vào năm 2021 - thấp hơn 500.000 bpd so với dự báo tháng 8 do nhu cầu Trung Quốc tăng trưởng thấp hơn. Sản lượng khai thác toàn cầu tháng 8 trung bình đạt 91,5 triệu bpd, giảm 9,7 triệu bpd so với cùng kỳ năm 2019 chủ yếu do tuân thủ tốt thỏa thuận OPEC+ cùng với việc cắt giảm khai thác tại Mỹ (tháng 8 đạt 10,8 triệu bpd). Sản lượng toàn cầu năm 2021 dự báo sẽ tăng 7,8 triệu bpd lên 99,3 triệu bpd. EIA dự báo dầu tồn kho thế giới sẽ tiếp tục giảm trong nửa cuối năm 2020 từ 3,1 - 3,7 triệu bpd và đến hết năm 2021. Ngay trong quý 3/2020 cầu sẽ vượt cung giúp thị trường đi vào quỹ đạo ổn định, đạt điểm cân bằng vào cuối năm 2021 trong khi giá dầu sẽ vẫn duy trì ở mức dưới 55 USD/thùng đến giữa năm 2021. Tuy nhiên, nếu làn sóng Covid-19 thứ 2 bùng phát mạnh, dẫn đến cách ly xã hội diện rộng, mọi thứ sẽ thay đổi hoàn toàn.\nBiểu đồ thể hiện cân đối giữa sản xuất và tiêu thụ nhiên liệu hàng quý trong thời gian các năm 2015 đến 2021, cho thấy tiêu dùng và sản xuất nhiên liệu quý 1 và 2 năm 2020 thấp nhất trong 5 năm và dự đoán sẽ tăng trong năm 2021, đạt bằng mức 2017, 2018. Viễn Đông\nNguồn: https://nangluongquocte.petrotimes.vn/",
        "ngay_dang": "29.09.2020",
        "ngay_crawl": "2025-09-10 07:27:51"
    },
    {
        "id": 2004,
        "title": "DẤU ẤN PVOIL TẠI GIẢI ĐUA XE ĐỊA HÌNH VOC 2020",
        "url": "https://www.pvoil.com.vn/dau-an-pvoil-tai-giai-dua-xe-dia-hinh-voc-2020",
        "content": "Nhà tài trợ PVOIL mang đến Giải đua xe ô tô địa hình Việt Nam 2020 những hoạt động hấp dẫn, thu hút sự quan tâm của các tay đua và khán giả. Diễn ra trong hai ngày 26-27/9 tại Làng Văn hóa Du lịch các dân tộc Việt Nam, Giải đua xe ô tô địa hình Việt Nam PVOIL Cup 2020 (PVOIL VOC 2020) đã kết thúc thành công vào cuối tuần qua. Tại giải đấu này, nhà tài trợ tên giải, Tổng Công ty dầu Việt Nam PVOIL đã mang đến nhiều hoạt động thú vị.\nCây xăng di động PVOIL Mobile\nTrước giờ khai mạc, khu vực PVOIL Zone thu hút sự chú ý của đông đảo các tay đua. Các vị lãnh đạo PVOIL và Ban tổ chức, Ban điều hành giải cùng nhau cắt băng khai trương, chào đón những chiếc xe đầu tiên vào đổ nhiên liệu tại cây xăng PVOIL di động. PVOIL cũng là đơn vị đầu tiên và duy nhất hiện nay ứng dụng công nghệ thanh toán điện tử, không cần tiền mặt khi mua xăng dầu. Ngoài ra, các đội đua còn được đích thân ông Cao Hoài Dương (Chủ tịch HĐQT PVOIL), ông Đoàn Văn Nhuộm (Tổng Giám đốc PVOIL) trao tận tay những món quà tặng là bộ chăm sóc xe PVOIL Care. Đây sẽ là những động viên kịp thời, tiếp thêm động lực để các tay đua thi đấu tốt hơn.\nNgay sau đó, màn biểu diễn drift mang đến cho khán giả một bữa tiệc mãn nhãn. Những pha drift, donut hình tròn xoay quay các thùng phi PVOIL được nhiều người hưởng ứng. Tại đây, các vị đại diện PVOIL cùng ông Khuất Việt Hùng – Phó Chủ tịch chuyên trách Ủy ban ATGT Quốc gia - có cơ hội lần đầu tiên được trải nghiệm trong khoang lái của một chiếc xe chạy drift. Âm thanh phát ra từ động cơ, tiếng lốp ma sát trên mặt đường hay khói xe... tất cả tạo nên một không khi hết sức sôi động. Đúng 8h sáng ngày 26/9, buổi lễ khai mạc PVOIL VOC 2020 chính thức diễn ra. Chương trình cũng hân hạnh nhận được sự tham gia của các lãnh đạo trung ương, các nhà tài trợ, bao gồm: Ông Khuất Việt Hùng – Phó Chủ tịch chuyên trách Ủy ban ATGT Quốc gia; Ông Cao Hoài Dương – Chủ tịch HĐQT PVOIL, Ông Nguyễn Đức Hoàng – Trưởng Ban tổ chức giải; Ông Ngô Việt Dũng – Trưởng Ban điều hành giải.\nĐại diện cho nhà tài trợ, ông Cao Hoài Dương có bài phát biểu nhận được nhiều sự đồng tình. Ông cho biết, sau nhiều năm đồng hành cùng VOC, PVOIL luôn tin tưởng OTV Media và diễn đàn Otofun trong công tác tổ chức và điều hành giải đấu. PVOIL cũng hy vọng rằng, trong nhiều năm tới, giải VOC sẽ ngày càng chuyên nghiệp hơn. Đồng thời, PVOIL cam kết gắn bó lâu dài cùng Giải đua xe ô tô định hình Việt Nam (Vietnam Offroad Cup – VOC). Để bắt đầu mỗi mùa giải VOC, nghi thức diễu hành qua cổng chào là truyền thống lâu đời của giải. Tại đây, ông Khuất Việt Hùng và vị lãnh đạo PVOIL cùng rất đông khán giả xếp hai bên cổng, chào mừng 80 đội đua, chúc các tay lái vững niềm tin, bản lĩnh để vượt qua các bài thi một cách tốt nhất.\nÔng Khuất Việt Hùng (phải) và ông Cao Hoài Dương (trái) phất cờ chào mừng các đội đua.\nĐồng hành cùng giải đấu, bên cạnh PVOIL Zone và cây xăng di động, gian hàng PVOIL tại khu vực lều trung tâm cũng mang đến cho khán giả nhiều trải nghiệm thú vị. Tại đây, khách tham quan sẽ có cơ hội tìm hiểu về các sản phẩm mà PVOIL đang sản xuất và phân phối. Với những khách hàng sử dụng xe, dầu nhớt đến từ công ty PVOIL Lube sẽ là những sản phẩm đáng tin cậy cho quá trình vận hành. Trong khi đó, bộ kit chăm sóc xe PVOIL Care được nhiều người yêu xe quan tâm, giúp chiếc xe trở nên đẹp hơn. Ngoài các sản phẩm liên quan đến xe ô tô, PVOIL còn sản xuất và phân phối nhiều loại nước uống giải khát với nguồn gốc xuất xứ rõ ràng. Sản phẩm nước khoáng Tiền Hải được lấy từ mỏ nước khoáng sâu 400m dưới biển. Nước uống hương hoa sen nhãn hiệu Wells là sản phẩm mới nhưng được nhiều khách hàng đón nhận. Đặc biệt, nước khoáng chanh muối đặc biệt được các tay đua sử dụng nhiều, giúp bù khoáng tốt cho sức khỏe, nhất là với những người thường xuyên vận động mạnh.\nSau hai ngày thi đấu căng thẳng, kịch tính, quyết liệt, PVOIL VOC 2020 cũng tìm ra những tay đua xứng đáng với các giải thưởng cao quý. Lễ bế mạc giải đua năm nay diễn ra vào lúc 18h30 chiều ngày 27/9, khi trời đã về tối. Ông Lê Ngọc Quang (Thành viên HĐQT PVOIL) cùng các vị đại diện PVOIL cũng có mặt tại buổi lễ này. Hai tay đua Vũ Ngọc Cường và Nguyễn Văn Luật đến từ đội 414 – A.B.O 4x4 vinh dự nhận được cúp, hoa và giải thưởng 80 triệu đồng dành cho phân hạng Mở rộng từ ông Lê Ngọc Quang - Thành viên HĐQT PVOIL. Đây cũng là hạng đấu cao nhất, căng thẳng nhất và gay cấn nhất tại PVOIL VOC 2020.\nÔng Lê Ngọc Quang nhận kỷ niệm chương\nPVOIL VOC 2020 đã chính thức khép lại. Những dấu ấn mà nhà tài trợ tên giải là Tổng Công ty dầu Việt Nam – PVOIL mang đến giải năm nay được đông đảo khán giả quan. Các thành viên Ban tổ chức, Ban điều hành, các đội đua và vận động viên đều nhận được những sự ủng hộ kịp thời, những phần quà to lớn không chỉ về mặt vật chất và tinh thần.\nAnh Vũ - Phan Linh Theo CSAT",
        "ngay_dang": "28.09.2020",
        "ngay_crawl": "2025-09-10 07:27:52"
    },
    {
        "id": 2005,
        "title": "Nhận định giá xăng dầu tuần tới (28/9-4/10): Dầu sẽ tăng mạnh trong tháng mới",
        "url": "https://www.pvoil.com.vn/nhan-dinh-gia-xang-dau-tuan-toi-289-410-dau-se-tang-manh-trong-thang-moi",
        "content": "Giá dầu thế giới đi xuống trong phiên 25/9, hai loại dầu chủ chốt là WTI và Brent đều giảm hơn 2% trong tuần qua. Bên cạnh đó, giá xăng dầu trong nước cũng được điều chỉnh giảm xuống theo tình hình thế giới. Ông Phil Flynn, nhà phân tích cấp cao của công ty môi giới đầu tư Price Futures Group cho biết nỗi lo sợ về làn sóng lây nhiễm COVID-19 thứ hai đang bao trùm thị trường dầu mỏ và điều đó đang kìm hãm giá dầu đi lên.\nNhận định giá xăng dầu tuần tới (28/9-4/10): Dầu sẽ tăng mạnh trong tháng mới.\nTại quốc gia tiêu thụ dầu hàng đầu thế giới là Mỹ, tình trạng lây nhiễm COVID-19 đang gia tăng ở khu vực Midwest trong khi thành phố New York, nơi bị ảnh hưởng nặng nề nhất vào mùa Xuân, đang xem xét các lệnh kiểm soát mới. Do đó, mức tiêu thụ nhiên liệu của Mỹ vẫn khá chậm chạp do đại dịch hạn chế hoạt động đi lại và cản trở đà phục hồi của nền kinh tế. Tính chung trong cả tuần qua, giá dầu Brent giảm 2,9% và dầu WTI giảm 2,1% dù chỉ có 2 phiên giảm giá và 3 phiên tăng. Ông Gary Cunningham, Giám đốc nghiên cứu thị trường tại Tradition Energy, có trụ sở tại Stamford, Connecticut, cho biết hiện các thông tin đều có vẻ bất lợi về triển vọng tiêu thụ nhiên liệu máy bay, bức tranh kinh tế toàn cầu có vẻ không còn “sáng sủa” như những nhận định trước đó. Bên cạnh đó, lượng dầu thô đổ ra thị trường toàn cầu có thể còn gia tăng và đẩy giá dầu xuống thấp hơn nữa trong tuần tới. Công ty dịch vụ năng lượng Baker Hughes Co cho biết, số lượng giàn khoan dầu của Mỹ đã tăng thêm sáu giàn lên 261 giàn trong tuần tính đến ngày 25/9. Cùng với đó, dựa trên việc theo dõi các tàu chở dầu, giới quan sát nhận định xuất khẩu dầu của Iran đã tăng mạnh trong tháng 10 bất chấp các lệnh trừng phạt của Mỹ. Goldman Sachs vẫn giữ nguyên dự báo giá dầu Brent đạt 49 USD/thùng vào cuối năm 2020 và 65 USD/thùng vào quý III/2021, bất chấp những diễn biến bất ổn tại Libya. Trong khi đó, Barclays nâng triển vọng giá dầu Brent năm 2020 lên 43 USD/thùng và 53 USD/thùng vào năm sau. Giá xăng dầu trong nước vừa được điều chỉnh hôm 26/9 và vẫn sẽ giữ nguyên mức này trong tuần tới. Cụ thể, giá xăng E5RON95 được điều chỉnh giảm 51 đồng/lít, trong khi giá xăng RON 95 được giữ nguyên. Mức giá bán lẻ tối đa với xăng E5 RON 92 là 14.215 đồng/lít, xăng RON 95 là 14.984 đồng/lít. Dầu diesel là 11.128 đồng/lít; dầu hỏa là 9.449 đồng/lít và dầu mazut là 10.826 đồng/kg. Nguồn tin : thoidai.com.vn",
        "ngay_dang": "28.09.2020",
        "ngay_crawl": "2025-09-10 07:27:52"
    },
    {
        "id": 2006,
        "title": "TT năng lượng TG ngày 25/9/2020: Giá dầu thay đổi nhẹ, khí tự nhiên tăng 6%",
        "url": "https://www.pvoil.com.vn/tt-nang-luong-tg-ngay-2592020-gia-dau-thay-doi-nhe-khi-tu-nhien-tang-6",
        "content": "Giá dầu thế giới ngày 25/9 thay đổi nhẹ, song có tuần giảm do lo ngại số trường hợp nhiễm COVID-19 tăng, sẽ khiến nhu cầu nhiên liệu suy giảm, trong khi có khả năng xuất khẩu dầu trở lại từ Libya sẽ bổ sung nguồn cung vào thị trường. Giá dầu Brent giảm 2 US cent xuống 41,92 USD/thùng, trong khi dầu thô Mỹ (WTI) tăng 3 US cent lên 40,34 USD/thùng. Tính chung cả tuần, giá dầu Brent giảm gần 3%, trong khi dầu thô Mỹ (WTI) giảm gần 2%. Tính chung từ đầu tháng đến nay, cả hai loại dầu đều có tháng giảm, với dầu Brent có tháng giảm đầu tiên trong 6 tháng. RBC Capital Markets cho biết: “Triển vọng về việc Libya trở lại thị trường gây áp lực giá\". Tồn trữ dầu thô, xăng và sản phẩm chưng cất của Mỹ đều giảm trong tuần trước. Hiện tại nhu cầu nhiên liệu tại Mỹ vẫn ở trong tình trạng ảm đạm do dịch bệnh hạn chế việc đi lại. Mức tiêu thụ xăng trung bình trong 4 tuần kết thúc vào tuần trước giảm 9% so với cùng kỳ năm trước. Giá khí tự nhiên tăng 6% Giá khí tự nhiên tại Mỹ tăng gần 6% vào thứ năm (25/9) do tồn trữ  thấp hơn so với dự kiến, sản lượng tiếp tục giảm và xuất khẩu khí  tự nhiên hóa lỏng (LNG) tăng. Cơ quan Thông tin Năng lượng Mỹ (EIA) cho biết, các công ty tiện ích của Mỹ chỉ bơm 66 tỷ feet khối (bcf) khí vào kho chứa trong tuần kết thúc ngày 18/9/2020. Con số này thấp hơn nhiều so với dự báo (78 bcf) của các nhà phân tích và so với mức 97 bcf trong cùng tuần năm trước đó và mức tăng trung bình trong 5 năm (2015-19) là 80 bcf. Giá khí tự nhiên kỳ hạn tháng 10/2020 trên sàn New York tăng 12,3 US cent tương đương 15,9% lên mức cao nhất trong một tuần đạt 2,248 USD/mmBtu. Thị trường biến động mạnh trong tuần này - giá giảm hơn 10% vào thứ hai (21/9) và tăng gần 16% vào thứ tư (23/9) - khi các nhà giao dịch đưa ra các hợp đồng kỳ hạn tháng 10 hết hạn vào ngày 28/9 và hợp đồng kỳ hạn tháng 11/2020 có giá cao hơn nhiều. Nguồn: VITIC/Reuters",
        "ngay_dang": "28.09.2020",
        "ngay_crawl": "2025-09-10 07:27:53"
    },
    {
        "id": 2007,
        "title": "Những khoảnh khắc ấn tượng tại PVOIL VOC 2020 (Ngày 1)",
        "url": "https://www.pvoil.com.vn/nhung-khoanh-khac-an-tuong-tai-pvoil-voc-2020-ngay-1",
        "content": "Bất chấp nắng nóng, các Vận động viên đã nỗ lực hết mình để hoàn thành xuất sắc các bài thi trong ngày thi đấu đầu tiên của Giải đua xe ô tô địa hình Việt Nam PVOIL Cup 2020 (PVOIL VOC 2020). Sáng nay (26/09) Giải đua xe Ô tô Địa hình lớn nhất Việt Nam PVOIL Cup 2020 (PVOIL VOC 2020) do diễn đàn Otofun.net tổ chức đã chính thức khai mạc. Chúng ta hãy cùng xem lại những khoảnh khắc ấn tượng của Giải trong ngày thi đấu thứ nhất:\nKhoảnh khắc BTC phất cờ  - chính thức khai mạc Giải PVOIL VOC 2020\nCác Vận động viên với những nụ cười rực rỡ...\nNhững biểu cảm thú vị...\nhầm hố và hiền lành...\nxinh đẹp và phong cách...\nĐội Media, \"Ô phở\"  đã chuẩn bị \"súng ống\" sẵn sàng...\nCác Vận động viên, các đội đua nỗ lực hết mình, cống hiến cho khán giả những màn thi đấu cực kỳ ấn tượng\nNói như MC - Bình luận viên Ngô Quốc Thắng: \" PVOIL VOC những năm gần đây ngày một chuyên nghiệp. Chuyên nghiệp đến mức trọng tài bỗng... trở nên nhàn. Họ không còn là người cầm cân nảy mực mà trở thành những người động viên, nhắc nhở để các VĐV thi đấu tốt .\nĐây là lý do vì sao nhiều người gọi PVOIL VOC là giải đấu của những người đam mê \"phá xe\"\nSau những nỗ lực không ngừng\n... là niềm vui vỡ òa khi về đích\nLà những nụ cười, sự cổ vũ nhiệt liệt đến từ các cổ động viên\nMời quý độc giả tiếp tục theo dõi và cổ vũ cho Giải Đua xe ô tô địa hình Việt Nam PVOIL Cup 2020. Giải đấu diễn ra trong 2 ngày 26 & 27/ 9 tại Làng văn hóa - du lịch các dân tộc Việt Nam, Đồng Mô - Hà Nội. Thu Hằng - Phan Linh Theo CSAT",
        "ngay_dang": "27.09.2020",
        "ngay_crawl": "2025-09-10 07:27:53"
    }
]