[
  {
    "id": "page_74_1",
    "title": "PV GAS ủng hộ 1,5 tỷ đồng cho chương trình phòng chống Covid tại Bệnh viện K Hà Nội",
    "url": "https://www.pvgas.com.vn/bai-viet/pv-gas-ung-ho-15-ty-dong-cho-chuong-trinh-phong-chong-covid-tai-benh-vien-k-ha-noi",
    "crawl_date": "2025-09-09 13:18:20"
  },
  {
    "id": "page_74_2",
    "title": "Petrovietnam giành 30 tỷ đồng ủng hộ Quỹ vắc-xin phòng Covid-19",
    "url": "https://www.pvgas.com.vn/bai-viet/petrovietnam-gianh-30-ty-dong-ung-ho-quy-vac-xin-phong-covid-19",
    "crawl_date": "2025-09-09 13:18:20"
  },
  {
    "id": "page_74_3",
    "title": "PV GAS thực hiện các chương trình ASXH 2021",
    "url": "https://www.pvgas.com.vn/bai-viet/pv-gas-thuc-hien-cac-chuong-trinh-asxh-2021",
    "crawl_date": "2025-09-09 13:18:20"
  },
  {
    "id": "page_74_4",
    "title": "Phòng chống đại dịch Covid bằng những hành động thiết thực",
    "url": "https://www.pvgas.com.vn/bai-viet/phong-chong-dai-dich-covid-bang-nhung-hanh-dong-thiet-thuc",
    "crawl_date": "2025-09-09 13:18:20"
  },
  {
    "id": "page_74_5",
    "title": "Hội nghị BCH Đảng bộ PV GAS lần thứ V – Nhiệm kỳ 2020-2025",
    "url": "https://www.pvgas.com.vn/bai-viet/hoi-nghi-bch-dang-bo-pv-gas-lan-thu-v-nhiem-ky-2020-2025",
    "crawl_date": "2025-09-09 13:18:20"
  },
  {
    "id": "page_74_6",
    "title": "Nhân ngày Khoa học Công nghệ Việt Nam 18/5  Petrovietnam phát triển khoa học công nghệ:  Biến những điều không thể thành có thể",
    "url": "https://www.pvgas.com.vn/bai-viet/nhan-ngay-khoa-hoc-cong-nghe-viet-nam-185-petrovietnam-phat-trien-khoa-hoc-cong-nghe-bien-nhung-dieu-khong-the-thanh-co-the",
    "crawl_date": "2025-09-09 13:18:20"
  },
  {
    "id": "page_74_7",
    "title": "PV GAS chủ động chuẩn bị ứng phó tình huống khẩn cấp",
    "url": "https://www.pvgas.com.vn/bai-viet/pv-gas-chu-dong-chuan-bi-ung-pho-tinh-huong-khan-cap",
    "crawl_date": "2025-09-09 13:18:20"
  },
  {
    "id": "page_74_8",
    "title": "Bản lĩnh người Dầu khí trong đại dịch Covid-19",
    "url": "https://www.pvgas.com.vn/bai-viet/ban-linh-nguoi-dau-khi-trong-dai-dich-covid-19",
    "crawl_date": "2025-09-09 13:18:20"
  },
  {
    "id": "page_74_9",
    "title": "Phát huy hiệu quả quản trị, Petrovietnam có bước tăng trưởng mạnh",
    "url": "https://www.pvgas.com.vn/bai-viet/phat-huy-hieu-qua-quan-tri-petrovietnam-co-buoc-tang-truong-manh",
    "crawl_date": "2025-09-09 13:18:20"
  },
  {
    "id": "page_74_10",
    "title": "PV GAS tiếp tục chấn chỉnh và tăng cường phòng chống dịch bệnh Covid-19  trong tình hình mới",
    "url": "https://www.pvgas.com.vn/bai-viet/pv-gas-tiep-tuc-chan-chinh-va-tang-cuong-phong-chong-dich-benh-covid-19-trong-tinh-hinh-moi",
    "crawl_date": "2025-09-09 13:18:20"
  },
  {
    "id": "page_74_11",
    "title": "PV GAS LPG tổ chức Đại hội đồng cổ đông thường niên năm 2021",
    "url": "https://www.pvgas.com.vn/bai-viet/pv-gas-lpg-to-chuc-dai-hoi-dong-co-dong-thuong-nien-nam-2021",
    "crawl_date": "2025-09-09 13:18:20"
  },
  {
    "id": "page_74_12",
    "title": "PV GAS D tổ chức thành công ĐHĐCĐ thường niên năm 2021: Thông qua 12 tờ trình, chia cổ tức năm 2020 20% vốn điều lệ",
    "url": "https://www.pvgas.com.vn/bai-viet/pv-gas-d-to-chuc-thanh-cong-dhdcd-thuong-nien-nam-2021-thong-qua-12-to-trinh-chia-co-tuc-nam-2020-20-von-dieu-le",
    "crawl_date": "2025-09-09 13:18:20"
  }
]