[
    {
        "id": "40a29504-2d24-4b1a-adcf-5c3201f2b44c",
        "title": "",
        "url": "https://fpt.com/vi/tin-tuc/su-kien/lien-danh-fpt-petro-south-tu-van-chuyen-doi-so-vietsovpetro",
        "content": "",
        "ngay_dang": "",
        "ngay_crawl": "2025-09-09 20:00:30"
    },
    {
        "id": "6e35f52d-25d9-4884-9b68-a2c22d226a65",
        "title": "Tong giam doc FPT duoc bau la Pho chu tich Hoi doanh nhan tre viet nam",
        "url": "https://fpt.com/vi/tin-tuc/tong-giam-doc-fpt-duoc-bau-la-pho-chu-tich-hoi-doanh-nhan-tre-viet-nam",
        "content": "",
        "ngay_dang": "19/08/2022",
        "ngay_crawl": "2025-09-09 20:00:31"
    },
    {
        "id": "bbfef177-df5d-4f79-a37f-ac47edf2a99a",
        "title": "Ứng dụng của Blockchain trong Chuyển đổi số doanh nghiệp",
        "url": "https://fpt.com/vi/tin-tuc/newsletter/blockchain-chia-khoa-vang-cho-chuyen-doi-so",
        "content": "Bên cạnh AI (trí tuệ nhân tạo), Big Data, Cloud và IoT (internet vạn vật), Blockchain (chuỗi khối) đóng một vai trò quan trọng trong quá trình chuyển đổi số toàn diện, giúp doanh nghiệp nâng cấp quy trình làm việc, tối ưu hóa hiệu quả vận hành.\nBlockchain là một cơ sở dữ liệu phân tán cho phép người dùng tạo và duy trì các giao dịch an toàn trên nhiều máy tính. Cấu trúc của dữ liệu trong blockchain hoàn toàn khác với cấu trúc của cơ sở dữ liệu truyền thống khi dữ liệu được lưu trữ trong các khối được liên kết với nhau dưới dạng chuỗi. Dữ liệu này không thể bị xoá hoặc sửa đổi nếu không có sự đồng ý từ những người dùng trong hệ thống mạng blockchain. Do đó, doanh nghiệp có thể sử dụng công nghệ chuỗi khối để theo dõi các đơn đặt hàng, giao dịch thanh toán trực tuyến nhằm nâng cao sự bảo mật, tính minh bạch cũng như ngăn chặn các giao dịch trái phép, giả mạo.\nThuật ngữ blockchain ngày nay trở nên vô cùng phổ biến khi được ứng dụng trong nhiều lĩnh vực của đời sống và trong hoạt động kinh doanh. Tuy nhiên, vẫn có nhiều lầm tưởng về công nghệ này, gây ra nhiều tranh cãi trong cộng đồng cũng như ảnh hưởng tới các quyết định ứng dụng blockchain.\n(Nguồn: McKinsey)\nKhi các doanh nghiệp ngày càng chuyển dịch hoạt động kinh doanh lên thị trường số, blockchain có tiềm năng trở thành công nghệ then chốt giúp tạo ra sự tin cậy và bảo mật cao cho người tiêu dùng, khách hàng, đối tác thương mại và kinh doanh trong thế giới kết nối số.\nThay vì được lưu trữ tập trung, blockchain là một cơ sở dữ liệu ảo được lưu trữ trong một mạng lưới mà mỗi người dùng trong mạng lưới đó đều có một bản sao của cơ sở dữ liệu. Cấu trúc phi tập trung kết hợp với việc sử dụng các mật mã giúp ngăn chặn việc rò rỉ thông tin trong cơ sở dữ liệu. Do đó, blockchain tạo ra mức độ tin cậy cực cao trong các giao dịch mà không cần người trung gian giám sát giao dịch.\nBlockchain mang lại sự minh bạch tối đa trong mọi giao dịch trong chuỗi cung ứng - từ việc thu mua nguyên liệu, sản xuất đến phân phối và bán sản phẩm. Điều này giúp khách hàng có thể truy xuất nguồn gốc của sản phẩm trong toàn bộ chuỗi cung ứng, từ đó giảm thiểu rủi ro một cách tối đa.\nVí dụ, blockchain đã giúp Alibaba đảm bảo chất lượng cũng như nguồn gốc của thực phẩm trong toàn bộ chuỗi cung ứng.Các nhà cung cấp trên nền tảng thương mại điện tử của Alibaba sẽ xác minh tính xác thực của các mặt hàng bằng cách sử dụng blockchain. Ví dụ như blockchain sẽ lưu trữ dữ liệu DNA của một con bò thông qua 1 gói steak, sau đó đánh dấu mặt hàng này bằng kỹ thuật số để xác thực chất lượng trong toàn bộ vòng đời sản phẩm. Khi khách hàng mua sắm, họ có thể dễ dàng quét mã QR trên bao bì để tìm hiểu thông tin của sản phẩm cũng như chỉ số chất lượng và nguồn gốc xuất xứ. Hệ thống này hiện đang được thử nghiệm ở Úc và New Zealand, rất nhiều loại thực phẩm trên có nguồn gốc từ các quốc gia này. Sắp tới, dự án thử nghiệm này sẽ được áp dụng sang các loại lô hàng khác để giảm thiểu các mặt hàng giả mạo trên Alibaba.\nSự thành công của blockchain trong việc tạo và quản lý các loại tiền điện tử như Bitcoin đã tạo ra một cuộc cách mạng về tiền tệ và tài chính. Blockchain hứa hẹn giảm thiểu gian lận, đảm bảo các giao dịch diễn ra nhanh chóng, an toàn, và giúp người dùng dễ theo dõi hơn so với ngân hàng truyền thống.\nMột ví dụ điển hình đó là việc Visa sử dụng blockchain để khởi chạy dịch vụ thanh toán B2B. Visa phát triển một nền tảng để xử lý các giao dịch giữa ngân hàng với ngân hàng một cách an toàn hơn và nhanh hơn, phục vụ cho việc xử lý các khoản thanh toán quốc tế của công ty.\nVisa sử dụng công nghệ dựa trên blockchain để tạo nhiều điều kiện thuận lợi cho các giao dịch từ ngân hàng gốc đến người nhận. Bên cạnh đó, Visa cũng triển khai thiết kế hệ thống đảm bảo kết hợp các tiêu chuẩn bảo mật dữ liệu của công ty.\nHợp đồng thông minh không chỉ có thể lưu trữ an toàn thông tin mà còn có thể tự động thay đổi dữ liệu theo cách đáng tin cậy. Các hợp đồng thông minh được cung cấp bởi blockchain được triển khai dựa trên các thỏa thuận được xác định trước, qua đó nâng cao sự minh bạch cũng như chống sự giả mạo. Điều này giúp doanh nghiệp tiết kiệm thời gian và tiền bạc, đồng thời đảm bảo sự tuân thủ của tất cả mọi người có liên quan.\nTheo một nghiên cứu của Deloitte, việc số hóa các phương tiện truyền thông đã gây ra tình trạng chia sẻ tràn lan các nội dung vi phạm bản quyền. Bằng việc sử dụng Blockchain, các công ty có thể bảo vệ dữ liệu triệt để, ngăn chặn việc vi phạm bản quyền đang phổ biến hiện nay. Chẳng hạn như blockchain có thể duy trì tính toàn vẹn của dữ liệu, cho phép các công ty quảng cáo nhắm mục tiêu đúng khách hàng và các nhạc sĩ nhận được tiền bản quyền thích hợp.\nNguồn tham khảo:\nhttps://www.mckinsey.com/capabilities/mckinsey-digital/our-insights/blockchain-beyond-the-hype-what-is-the-strategic-business-value\nhttps://builtin.com/blockchain/blockchain-applications\nhttps://www.itransition.com/blog/reallife-examples-of-blockchainbased-digital-transformation",
        "ngay_dang": "24/10/2022",
        "ngay_crawl": "2025-09-09 20:00:32"
    },
    {
        "id": "121f51b4-a9dc-4bb5-9308-b5eeae47dd9c",
        "title": "",
        "url": "https://fpt.com/vi/tin-tuc/tin-fpt/truong-gia-binh-nhandan-special-2-2023",
        "content": "",
        "ngay_dang": "",
        "ngay_crawl": "2025-09-09 20:00:35"
    },
    {
        "id": "1ce3e70b-9458-4830-a480-ee5d23f30a81",
        "title": "",
        "url": "https://fpt.com/vi/tin-tuc/tin-fpt/fpt-va-ba-huan-di-dau-chuyen-doi-so-trong-linh-vuc-nong-nghiep",
        "content": "",
        "ngay_dang": "",
        "ngay_crawl": "2025-09-09 20:00:36"
    },
    {
        "id": "47980fc5-d093-45ab-935b-6acb703598ac",
        "title": "",
        "url": "https://fpt.com/vi/tin-tuc/tin-fpt/news-detail",
        "content": "",
        "ngay_dang": "",
        "ngay_crawl": "2025-09-09 20:00:37"
    },
    {
        "id": "fc291a65-acc0-4493-b1c0-eabb7e24e526",
        "title": "FPT nhận quyền sử dụng đất cho dự án mở rộng hệ thống giáo dục tại FPT City Đà Nẵng",
        "url": "https://fpt.com/vi/tin-tuc/fpt-nhan-quyen-su-dung-dat-cho-du-an-mo-rong-he-thong-giao-duc-tai-fpt-city-da-nang",
        "content": "Ngày 12/12, FPT và FPT City đã ký kết hợp đồng giao nhận quyền sử dụng đất cho dự án mở rộng hệ thống giáo dục tại Khu đô thị công nghệ FPT Đà Nẵng.\nLễ ký kết đồng giao nhận quyền sử dụng đất cho dự án mở rộng hệ thống giáo dục tại Khu đô thị công nghệ FPT Đà Nẵng giữa FPT và FPT City\nTham gia Lễ ký kết về phía FPT có TS. Lê Trường Tùng, Tổng Giám đốc Công ty TNHH Giáo dục FPT, Chủ tịch Hội đồng trường Trường Đại học FPT; ông Nguyễn Hữu Hiệp, Trưởng ban Đầu tư và Xây dựng Tổ chức Giáo dục FPT; ông Huỳnh Tấn Châu, Giám đốc Văn phòng Tổ chức Giáo dục FPT tại Đà Nẵng cùng đại diện lãnh đạo khác.\nĐại diện FPT City có ông Nguyễn Văn Lộc, Tổng Giám đốc FPT City, bà Trương Thị Linh Kiều, Phó Tổng Giám đốc FPT City, ông Phạm Thế Trường, Giám đốc Ban quản lý các dự án xây dựng FPT City cùng các cán bộ liên quan.\nTheo nội dung ký kết, FPT có quyền sử dụng khu đất có diện tích hơn 8.000 m2 tại Khu đô thị công nghệ FPT, phường Hòa Hải, quận Ngũ Hành Sơn, thành phố Đà Nẵng. Diện tích đất cùng toàn bộ hạ tầng kỹ thuật điện nước, mốc giới, hiện trạng và tài sản hiện có trên khu đất sẽ được chuyển giao sử dụng cho FPT, phục vụ dự án mở rộng hệ thống giáo dục của FPT tại Đà Nẵng.\nPhát biểu tại Lễ ký kết, TS. Lê Trường Tùng cho biết: “Đà Nẵng với FPT City là nơi có hiện diện của nhiều đơn vị thành viên thuộc mảng giáo dục FPT. Điều này góp phần mang đến sức sống cho khu đô thị nói riêng và thành phố Đà Nẵng nói chung”. TS. Lê Trường Tùng cũng cảm ơn sự phối hợp, hỗ trợ từ FPT City trong quá trình phát triển các campus giáo dục của FPT tại Đà Nẵng.\nTS. Lê Trường Tùng phát biểu tại Lễ ký kết\nĐáp lại phần chia sẻ của TS. Lê Trường Tùng, ông Nguyễn Văn Lộc, Tổng Giám đốc FPT City gửi lời cảm ơn FPT đã góp phần vào sự phát triển sôi động của FPT City tại Đà Nẵng .\nÔng Nguyễn Văn Lộc, Tổng Giám đốc FPT City\nLễ ký kết hợp đồng chuyển giao quyền sử dụng đất này là dấu mốc cho quyết tâm phát triển của FPT trong mảng giáo dục tại Đà Nẵng và mong muốn đồng hành, góp phần đảm bảo nguồn nhân lực cho sự phát triển bền vững của thành phố trong giai đoạn tiếp theo, đặc biệt là nhân lực thành thạo công nghệ cao như AI, STEM, Robotic...",
        "ngay_dang": "19/08/2022",
        "ngay_crawl": "2025-09-09 20:00:38"
    },
    {
        "id": "ae517132-cbe0-4e2d-ae7f-12d451b361e2",
        "title": "Thong bao chinh thuc ve viec to chuc le vieng ong Hoang Nam Tien",
        "url": "https://fpt.com/vi/tin-tuc/thong-bao-chinh-thuc-ve-viec-to-chuc-le-vieng-ong-hoang-nam-tien",
        "content": "",
        "ngay_dang": "19/08/2022",
        "ngay_crawl": "2025-09-09 20:00:40"
    },
    {
        "id": "ea0865fb-ea32-4c71-bb54-6e907c23945a",
        "title": "FPT ký kết hai thỏa thuận hợp tác thúc đẩy chuyển đổi số tỉnh Thừa Thiên Huế",
        "url": "https://fpt.com/vi/tin-tuc/thong-cao-bao-chi/fpt-ky-ket-hai-thoa-thuan-hop-tac-thuc-day-chuyen-doi-so-tinh-thua-thien-hue",
        "content": "Thừa Thiên Huế, ngày 18/08/2022, trong khuôn khổ Tuần lễ chuyển đổi số - Huế 2022, Tập đoàn FPT và công ty thành viên đã ký kết hai thỏa thuận hợp tác thúc đẩy chuyển đổi số tỉnh Thừa Thiên Huế đến năm 2025.\nCụ thể, Tập đoàn FPT ký kết hợp tác chuyển đổi số tổng thể toàn diện với UBND tỉnh Thừa Thiên Huế. Công ty TNHH Hệ thống thông tin FPT (FPT IS - công ty thành viên của Tập đoàn FPT) ký kết hợp tác đẩy mạnh chuyển đổi số ngành y tế với Sở Y tế tỉnh Thừa Thiên Huế.\nĐây cũng là địa phương thứ 22 trên toàn quốc, FPT đồng hành hợp tác đẩy mạnh chuyển đổi số trên cả ba trụ cột kinh tế số - xã hội số - chính phủ số.\nÔng Nguyễn Văn Khoa, Tổng Giám đốc FPT ký biên bản hợp tác chiến lược với UBND tỉnh Thừa Thiên Huế\nTheo nội dung của hai thỏa thuận hợp tác, tỉnh Thừa Thiên Huế và Tập đoàn FPT, FPT IS sẽ tập trung đẩy mạnh hợp tác trong một số lĩnh vực trọng điểm như tư vấn và triển khai các ứng dụng chuyển đổi số, phát triển hệ thống giáo dục liên cấp chất lượng cao, triển khai y tế thông minh, thương mại điện tử, thanh toán không dùng tiền mặt….\nTrong lĩnh vực y tế thông minh, hai bên sẽ xem xét tích hợp dịch vụ chăm sóc sức khoẻ, phòng bệnh thông minh vào ứng dụng Hue-S phục vụ việc theo dõi, chăm sóc sức khỏe cho người dân trên địa bàn tỉnh Thừa Thiên Huế và các tỉnh lân cận, đồng thời thúc đẩy triển khai dịch vụ khám chữa bệnh thông minh bao gồm bệnh án điện tử, bệnh viện thông minh, bệnh viện không giấy tờ; tích hợp nền tảng AI Chatbot, AI Voicebot phục vụ người dân/người bệnh; triển khai hệ thống quản lý hình ảnh (PACS) dùng chung toàn mạng lưới y tế điều trị của tỉnh; xây dựng kiến trúc y tế điện tử hình thành trục tích hợp thông tin quản lý ngành y tế. Là đơn vị đồng hành cùng hơn 300 bệnh viện và 20 Sở Y tế trên toàn quốc, FPT IS tự tin sẽ cùng Sở Y tế tỉnh thúc đẩy nhanh chóng quá trình chuyển đổi số hiệu quả theo mô hình lấy người bệnh làm trung tâm.\nTrong lĩnh vực thanh toán không dùng tiền mặt, FPT phối hợp với các đơn vị chức năng của tỉnh nâng cấp, phát triển hạ tầng thanh toán dịch vụ công, dịch vụ tiện ích không dùng tiền mặt hoạt động an toàn, hiện đại, hiệu quả và có khả năng kết nối, tích hợp với các hệ thống khác. Đồng thời, lên kế hoạch tổ chức các chương trình giúp doanh nghiệp và hộ gia đình bán sản phẩm tại Thừa Thiên Huế, đưa các sản phẩm của Thừa Thiên Huế ra toàn quốc thông qua nền tảng thương mại điện tử Sendo.\nĐồng thời, hai bên cũng sẽ phối hợp triển khai các chương trình đào tạo ngắn hạn và chuyên sâu về nâng cao nhận thức chuyển đổi số, trang bị kỹ năng số, sử dụng các sản phẩm chuyển đổi số …. cho các cấp lãnh đạo, cán bộ công chức, cán bộ viên chức, các doanh nghiệp/hộ kinh doanh/người dân trên địa bàn tỉnh.\nTỉnh Thừa Thiên Huế luôn được đánh giá là một trong những địa phương đi đầu cả nước trong công tác chuyển đổi số. Năm 2021, tỉnh Thừa Thiên Huế đứng thứ 2/63 tỉnh thành về mức độ chuyển đổi số cấp tỉnh trên cả ba trụ cột kinh tế số - xã hội số - chính phủ số. Nền tảng Hue-S sau 3 năm triển khai đã có gần 900.000 tài khoản, 17 triệu lượt truy cập, gần như đã tiếp cận được với hầu hết công dân. Tỉnh đặt mục tiêu năm 2025 đạt 100% tiêu chí Chính quyền số, hơn 90% dịch vụ công đạt cấp 4, kinh tế số chiếu 15 - 20% GRDP, 100% cơ quan triển khai Cloud và có hơn 300 doanh nghiệp công nghệ số.\nCũng trong khuôn khổ của sự kiện, trong vai trò doanh nghiệp tiên phong chuyển đổi số quốc gia, FPT đã tham gia nhiều hoạt động quan trọng gồm Tọa đàm, Diễn đàn, Triển lãm tại Tuần lễ chuyển đổi số - Huế 2022 với chủ đề Chuyển đổi số tạo đà đẩy nhanh phát triển kinh tế - xã hội.\nĐiều phối Tọa đàm “Phát triển doanh nghiệp công nghệ số Tỉnh Thừa Thiên Huế và tham vấn định hướng giải pháp chuyển đổi số cho các ngành, địa phương tỉnh Thừa Thiên Huế”, ông Nguyễn Văn Khoa, Chủ tịch VINASA, Tổng Giám đốc FPT cho biết, VINASA và các doanh nghiệp sẽ đồng hành với chính quyền tỉnh xây dựng chiến lược và thực thi chuyển đổi số hiệu quả nhất cũng như nghiên cứu, đầu tư, phát triển công nghệ số, nhân lực hỗ trợ tỉnh trong quá trình chuyển đổi số. Đặc biệt, VINASA sẽ tham vấn định hướng chuyển đổi số cho di sản văn hoá của tỉnh để tạo điều kiện phát triển kinh tế số, xã hội số….\nChia sẻ tại Diễn đàn “Chuyển đổi số tạo đà đẩy nhanh phát triển kinh tế - xã hội” về chủ đề Dữ liệu nền tảng quan trọng thúc đẩy chuyển đổi số Huế, ông Nguyễn Văn Khoa nhận định không có quy hoạch chia sẻ dữ liệu sẽ dẫn đến những khó khăn lớn cho quá trình chuyển đổi số, phát triển quốc gia số. Hiện Việt Nam sở hữu 10,6 nghìn tập dữ liệu mở, bằng 10% Úc, 0,75% châu Âu. Còn với tỉnh Thừa Thiên Huế, theo phân tích của VINASA, đây là một trong những địa phương đi đầu về chia sẻ dữ liệu của cả nước. Tuy nhiên, tỉnh vẫn chưa có chiến lược quy hoạch, dữ liệu tản mát nên chưa thể khai thác hiệu quả. Do đó, ông Khoa đưa ra đề xuất tỉnh cần xây dựng chiến lược quy hoạch, xây dựng, khai thác và chia sẻ dữ liệu, để từ đó, làm giàu, chuẩn hoá khai thác dữ liệu hiệu quả phục vụ hiệu quả cho các chương trình, hoạt động phát triển kinh tế xã hội của tỉnh.\nÔng Nguyễn Văn Khoa, Tổng Giám đốc FPT phát biểu tại lễ ký kết\nTrong các phiên tọa đàm và hội thảo của sự kiện, đại diện FPT và các công ty thành viên đã đưa ra một số đề xuất thúc đẩy chuyển đổi số phục vụ kết nối liên thông đa chiều, nâng cao hiệu lực, hiệu quả quản lý, điều hành, sản xuất kinh doanh cho các đơn vị, doanh nghiệp trên địa bàn tỉnh.\nTại khu vực Triển lãm, FPT cũng đã trình diễn hai sản phẩm tiêu biểu thuộc nhóm các sản phẩm liên quan đến phát triển đô thị thông minh, thanh toán không dùng tiền mặt là FPT Camera và Foxpay. FPT Camera là giải pháp camera an ninh ứng dụng Cloud và AI đồng bộ, toàn diện duy nhất tại Việt Nam cho phép giám sát, lưu trữ, quản lý thiết bị camera, dữ liệu và người dùng trên nền tảng điện toán đám mây. Bộ giải pháp thanh toán số toàn diện Foxpay cho khách hàng là người dùng cuối, doanh nghiệp và chính quyền. Hiện Foxpay trong tiến trình tích hợp vào các nền tảng dịch vụ công, mua sắm, du lịch …. đang được người dân, doanh nghiệp tỉnh Thừa Thiên Huế sử dụng thường xuyên, tạo trải nghiệm liền mạch, thân thiện khi thanh toán. Đặc biệt, Foxpay cũng bao gồm các giải pháp thanh toán dịch vụ công, hoá đơn tiện ích và mua sắm tại cửa hàng, siêu thị... giúp các doanh nghiệp, hộ kinh doanh chủ động mở rộng hệ sinh thái số cho người dùng cuối.\nTuần lễ chuyển đổi số - Huế 2022 do UBND tỉnh Thừa Thiên Huế và Hiệp hội Doanh nghiệp phần mềm và Dịch vụ CNTT Việt Nam (VINASA) phối hợp tổ chức nhằm nâng cao nhận thức chuyển đổi số trong các cấp, các ngành, các địa phương xây dựng Chính quyền số, hình thành cộng đồng doanh nghiệp chuyển đổi số và thúc đẩy phát triển xã hội số, kinh tế số.",
        "ngay_dang": "18/08/2022",
        "ngay_crawl": "2025-09-09 20:00:42"
    },
    {
        "id": "a256dcde-80ea-4136-af5a-08601cd2eebc",
        "title": "FPT Software và Shinsegae I&C hợp tác chiến lược thúc đẩy kinh doanh",
        "url": "https://fpt.com/vi/tin-tuc/tin-fpt/fpt-software-va-shinsegae-ic-hop-tac-chien-luoc-thuc-day-kinh-doanh",
        "content": "FPT Software (Công ty thành viên của Tập đoàn FPT) vừa ký kết thỏa thuận hợp tác chiến lược với Shinsegae I&C, Công ty công nghệ bán lẻ toàn cầu chuyên tạo ra các giá trị mới dựa trên công nghệ số - trực thuộc Tập đoàn bán lẻ khổng lồ Shinsegae Hàn Quốc. Thỏa thuận hợp tác này nhằm thúc đẩy hoạt động của trung tâm cung cấp công nghệ số toàn cầu tại Việt Nam. Trung tâm này được kỳ vọng sẽ giúp hai bên đẩy mạnh cung cấp, chuyển giao công nghệ số trong khu vực thông qua nguồn nhân lực số tài năng và các dịch vụ phần mềm chất lượng cao. Trung tâm dự kiến sẽ đi vào hoạt động vào tháng 12 năm 2022.\nGiám đốc Điều hành FPT Software (thứ 6 từ trái sang) và Giám đốc điều hành Shinsegae I&C (thứ 7 từ trái sang) tại lễ ký kết hợp tác chiến lược tại Seoul, Hàn Quốc\n“Trong bối cảnh thiếu hụt nhân lực công nghệ chất lượng cao đang diễn ra trên toàn thế giới, FPT Software cũng không ngừng nỗ lực để thu hút và giữ chân những tài năng công nghệ giỏi nhất để cung cấp dịch vụ với chất lượng tốt nhất cho khách hàng. Vì vậy, chúng tôi hy vọng sự hợp tác này sẽ giúp tận dụng nguồn lực của cả hai công ty”, Giám đốc Điều hành FPT Software Trần Đăng Hòa cho biết.\nTheo Viện Nghiên cứu và Chính sách Phần mềm (SPRi - Hàn Quốc), việc thiếu hụt kỹ sư phần mềm đang là vấn đề nổi cộm của các công ty tại Hàn Quốc. Có tới, 76,3% các công ty phần mềm Hàn Quốc đang thiếu các kỹ sư phần mềm được đào tạo bài bản.\nLà công ty công nghệ hàng đầu, FPT Software và Shinsegae I&C luôn chú trọng phát triển đội ngũ nhân tài và không ngừng nâng cao năng lực công nghệ.\nTừ năm 2019, Shinsegae I&C đã hợp tác tiếp cận nguồn nhân lực dồi dào và các giải pháp công nghệ hoàn chỉnh của FPT Software. Với mô hình kết hợp giữa các trung tâm nguồn lực tại Việt Nam và trên toàn cầu, FPT Software đã giúp Shinsegae hỗ trợ kịp thời và tiết kiệm chi phí cho các khách hàng và đối tác trên phạm vi toàn cầu.",
        "ngay_dang": "17/08/2022",
        "ngay_crawl": "2025-09-09 20:00:43"
    },
    {
        "id": "e0af8714-39d3-413e-b6c5-6e0d117307dd",
        "title": "Ba giải pháp số của FPT Software giành giải Vàng và Bạc tại Giải thưởng Kinh doanh Quốc tế năm 2022",
        "url": "https://fpt.com/vi/tin-tuc/tin-fpt/ba-giai-phap-so-cua-fpt-software-gianh-giai-vang-va-bac-tai-giai-thuong-kinh-doanh-quoc-te-nam-2022",
        "content": "Ba giải pháp số của FPT Software (Công ty thành viên của Tập đoàn FPT) gồm: FPT CloudSuite, akaAT và Usee vừa được Stevie Awards (Giải thưởng kinh doanh quốc tế) vinh danh ở hạng mục Giải pháp Công nghệ Kinh doanh (Business Technology Solution).\nakaAT, FPT CloudSuite và Usee của FPT Software được vinh danh tại Stevie Awards thường niên lần thứ 19\nTrong đó, FPT CloudSuite - Bộ giải pháp quản lý multi-cloud (đa đám mây) hỗ trợ doanh nghiệp quản lý tài nguyên, đảm bảo tiêu chuẩn bảo mật và tối ưu hóa chi phí trên nền tảng multi-cloud giành giải Vàng. FPT CloudSuite giúp doanh nghiệp dễ dàng thử nghiệm, triển khai ý tưởng trên môi trường Cloud nhanh 20-30% so với phương pháp truyền thống; giảm thiểu đến 20-30% rủi ro bảo mật trên môi trường Cloud; tối ưu đến 80% chi phí sử dụng.\nSản phẩm kiểm thử tự động - akaAT dành giải Bạc. Đây là công cụ đắc lực giúp các doanh nghiệp tăng hiệu quả quá trình kiểm thử và tối đa hóa phạm vi kiểm thử. Không chỉ giúp cải thiện chất lượng, akaAT còn giúp quá trình kiểm thử nhanh hơn nhiều lần, đồng thời giảm thiểu các chi phí liên quan, tăng hiệu quả đầu tư, tăng cường tinh thần làm việc của nhân viên khi thay thế các công việc lặp đi lặp lại. Sản phẩm akaAT đã tiết kiệm được chi phí, nguồn lực và thời gian rất đáng kể cho nhiều khách hàng trong các lĩnh vực khác nhau như: VnExpress, Bảo Việt Nhân Thọ, VideoVisit Healthcare…\nNền tảng phân tích dữ liệu - Usee dành giải Bạc. Dựa trên nguồn tài nguyên là dữ liệu khách hàng sẵn có, Usee đưa ra dự báo về nhu cầu của khách hàng theo khu vực cùng các chỉ số kinh doanh cần thiết cho quá trình hoạt động và vận hành. Nhờ vậy, giải pháp giúp doanh nghiệp lên kế hoạch quản lý và điều phối chuỗi cung ứng hiệu quả, cắt giảm chi phí và tiết kiệm nhân lực, tăng cường trải nghiệm khách hàng và cải thiện mối quan hệ đối tác của doanh nghiệp.Những đề cử chiến thắng này là một phần trong các giải pháp kỹ thuật số của FPT Software nhằm tối ưu hóa hoạt động của các quy trình kinh doanh khác nhau, từ đó thúc đẩy quá trình chuyển đổi kỹ thuật số.\nStevie Awards được biết đến là “Oscar của giới doanh nghiệp ”, giải thưởng hàng đầu thế giới nhằm tôn vinh và công nhận những thành tựu, đóng góp tích cực của các chuyên gia, tổ chức trên toàn thế giới. Đặc biệt, Giải thưởng kinh doanh quốc tế – International Business Awards trở thành một trong những giải thưởng uy tín được các doanh nghiệp, tổ chức hàng đầu trên thế giới như Google, IBM, Dell Technologies, NVIDIA… nỗ lực để đạt được.\nGiải thưởng thu hút hơn 3.700 đề cử từ 67 quốc gia và vùng lãnh thổ tranh tài ở nhiều hạng mục, bao gồm Công ty của năm, Sản phẩm hoặc dịch vụ mới tốt nhất của năm, Giám đốc điều hành của năm, cùng nhiều hạng mục khác. Hơn 300 chuyên gia trên toàn cầu sẽ cùng tham gia đánh giá và bình chọn các đề cử ở từng hạng mục.",
        "ngay_dang": "16/08/2022",
        "ngay_crawl": "2025-09-09 20:00:44"
    },
    {
        "id": "6fe37b95-6b51-496f-9995-21ab45d82f15",
        "title": "Khai phá cơ hội của kỷ nguyên Metaverse",
        "url": "https://fpt.com/vi/tin-tuc/newsletter/7-buoc-khai-pha-co-hoi-cua-ky-nguyen-metaverse",
        "content": "Metaverse (tạm dịch là đa vũ trụ ảo) được dự đoán trở thành một tương lai mới của Internet. Theo một báo cáo của McKinsey, giá trị của Metaverse sẽ đạt tới con số 5 nghìn tỉ USD vào năm 2030. Vậy những lĩnh vực nào có thể ứng dụng Metaverse và doanh nghiệp cần làm gì để tiếp cận và khai phá thị trường tiềm năng này?\nMetaverse - nơi tái hiện sống động trải nghiệm đời thực trong môi trường số, ngày càng bùng nổ mạnh mẽ trên toàn thế giới. Metaverse được đề cập lần đầu tiên vào năm 1992 bởi Neal Stephenson trong cuốn sách Snow Crash. Trong đó Metaverse được miêu tả là một thế giới ảo nơi mỗi người là một nhân dạng số riêng biệt và có thể tương tác, vui chơi, bàn luận, học tập, và rèn luyện. Năm 2021, số lượng tìm kiếm trên Google cho từ “Metaverse” đã tăng vọt 7.200%, và nền tảng trò chơi trực tuyến Metaverse “Roblox” đã đạt hơn 55 triệu người dùng hoạt động hàng ngày vào tháng 2 năm 2022.\nCác gã công nghệ khổng lồ trên thế giới cũng đang đầu tư mạnh mẽ vào thị trường Metaverse. Meta đã cam kết đầu tư hơn 10 tỷ USD vào bộ phận Reality Labs, cùng với 20 chuyên sản xuất phần cứng liên quan đến Metaverse (kính thực tế ảo - VR). Microsoft lên kế hoạch mua lại công ty trò chơi Activision Blizzard trị giá 69 tỷ USD và sẽ cung cấp “các khối xây dựng” cho Metaverse.\nKết quả 1 cuộc khảo sát của McKinsey với hơn 3.400 người tiêu dùng và giám đốc điều hành cũng cho thấy sự thích thú về Metaverse. Gần 60% người tiêu dùng sử dụng phiên bản đầu tiên của Metaverse hào hứng với việc chuyển đổi các hoạt động hàng ngày sang Metaverse. Khoảng 95% lãnh đạo doanh nghiệp mong đợi Metaverse có tác động tích cực đến ngành kinh doanh của họ trong vòng 5 đến 10 năm tới.\nVới tiềm năng tạo ra giá trị khổng lồ lên tới 5 nghìn tỷ USD vào năm 2030, các doanh nghiệp đứng trước rất nhiều cơ hội để ứng dụng Metaverse, cung cấp trải nghiệm độc đáo cho khách hàng, tăng cường hiệu quả kinh doanh.\nGiáo dục : Metaverse mang lại cho người học những trải nghiệm chân thực hơn. Trường Quản lý Rady của Đại học California tại San Diego – Mỹ sử dụng một khuôn viên ảo cho phép sinh viên tham gia vào các bài giảng online, gặp gỡ - trao đổi trong không gian mở sáng tạo, đột phá. Hay không gian lớp học ảo được phát triển bởi Akaverse (FPT) cũng giúp học sinh có avatar riêng biệt để cùng trao đổi, học tập, tương tác với nhau.\nBán lẻ : Metaverse giúp doanh nghiệp tung ra nhiều trải nghiệm mua sắm mới lạ để thu hút khách hàng, quảng bá thương hiệu và thiết lập cửa hàng “ảo” tiếp cận khách hàng toàn cầu. Nhiều nhà bán lẻ nội thất như Crate & Barrel, Walmart, West Elm và Wayfair đã hợp tác với Pinterest để sử dụng công nghệ thực tế ảo tăng cường (AR), giúp người tiêu dùng trải nghiệm trực tiếp cách bài trí đồ nội thất trong chính căn nhà của họ trước khi quyết định mua sắm.\nTài chính : Metaverse tập hợp các mạng xã hội trực tuyến, trò chơi, tiền điện tử và các tài sản kỹ thuật số đa dạng. Ngân hàng KB Kookmin của Hàn Quốc tạo ra các “thị trấn tài chính” ảo, các trung tâm viễn thông và không gian tương tác ảo.\nThời trang : Những thử nghiệm ban đầu của ngành thời trang với thế giới ảo phần lớn là việc ra mắt quần áo ảo. Gucci đã bán một phiên bản ảo của chiếc túi Dionysus với giá tương đương 6 đô la trên Roblox, sau đó mỗi chiếc túi này đã được đặt giá thầu lên tới hơn 4.000 đô la khi được bán lại trên thị trường đồ cũ, cao hơn giá của một chiếc túi thật.\nGiải trí: Gaming (trò chơi trực tuyến) là lĩnh vực giải trí đầu tiên bước vào Metaverse với những trò chơi nổi tiếng như Roblox và Fortnite. Bên cạnh đó, một số nhạc sĩ nổi tiếng cũng lên kế hoạch tổ chức các buổi biểu diễn trên nhiều nền tảng khác nhau trong Metaverse. Marshmello, Travis Scott, Ariana Grande và ca sĩ Ấn Độ Daler Mehndi là một trong số nhiều nghệ sĩ đã tạo được dấu ấn trong thế giới ảo.\nTheo quan điểm của chuyên gia McKinsey, các công ty phải xem xét Metaverse có thể tác động tích cực và tiêu cực như thế nào đến doanh nghiệp để từ đó đưa ra chiến lược phù hợp.\nDưới đây là 7 bước xây dựng chiến lược phát triển với Metaverse mà các doanh nghiệp có thể tham khảo:\nBước 1 : Doanh nghiệp cần xác định các mục tiêu rõ ràng khi bước chân vào thị trường Metaverse. Đó là để tạo ra nhu cầu mới, xây dựng cộng đồng hay là tạo các luồng doanh thu mới. Những mục tiêu này đóng vai trò vô cùng quan trọng, là kim chỉ nam cho việc phát triển của sản phẩm dịch vụ với Metaverse.\nBước 2 . Xác định vai trò của doanh nghiệp trong hệ sinh thái Metaverse. Doanh nghiệp có thể lựa chọn việc xây dựng các trải nghiệm mới cho người dùng trong nhiều lĩnh vực khác nhau, tạo điều kiện tương tác hay phát triển cơ sở hạ tầng cho Metaverse như xây dựng thành phần phần cứng, công nghệ Blockchain, AI, Big Data, Internet of Things (IOT),…\nBước 3. Tung ra các dự án đầu tiên và các trường hợp sử dụng (use cases) về Metaverse. Doanh nghiệp có thể thử nghiệm các cơ hội mới như:\nChẳng hạn như một use cases điển hình trong lĩnh vực Chăm sóc sức khoẻ là 2 công cụ khá phổ biến trong đại dịch: Telemedicine và Telehealth đã giúp bệnh nhân và bác sĩ có thể tương tác trong các phòng khám 3D ảo, giúp tăng hiệu quả khám chữa bệnh đồng thời hạn chế tiếp xúc, giảm nguy cơ lây nhiễm bệnh.\nBước 4. Theo dõi các chỉ số phù hợp để đo lường hiệu quả ban đầu trong ngắn hạn, từ đó lên kế hoạch thử nghiệm các phương án dài hạn trong tương lai. Việc phân tích các chỉ số giúp doanh nghiệp đưa ra các đánh giá kịp thời, làm cơ sở cho các quyết định về chiến lược phát triển trong tương lai.\nBước 5 . Phân tích thêm về người dùng, tìm hiểu hành vi của họ trên các nền tảng khác nhau và đưa ra các nghiên cứu chi tiết để tối ưu sản phẩm một cách phù hợp với nhu cầu của khách hàng.\nBước 6 . Bắt đầu kế hoạch mở rộng quy mô phát triển thông qua việc tìm kiếm nhân tài, thiết lập cơ sở hạ tầng công nghệ cũng như các công cụ cần thiết nhằm tăng tốc quá trình phát triển sản phẩm dịch vụ.\nBước 7 . Đưa Metaverse vào chiến lược kinh doanh và mô hình vận hành của doanh nghiệp, đồng thời xác định rõ ràng ai sẽ chịu trách nhiệm quản lý dự án.\nTuy nhiên, các chuyên gia của Gartner cũng cho rằng việc áp dụng công nghệ Metaverse vẫn còn non trẻ và manh mún, doanh nghiệp nên hạn chế đầu tư nhiều vào một số lĩnh vực Metaverse cụ thể. Vẫn còn quá sớm để xác định khoản đầu tư nào sẽ khả thi trong dài hạn, do đó, doanh nghiệp cần ưu tiên học hỏi, khám phá và chuẩn bị cho Metaverse trước khi triển khai.\nNguồn tham khảo:\nhttps://www.gartner.com/en/articles/what-is-a-metaverse\nhttps://www.gartner.com/en/newsroom/press-releases/2022-02-07-gartner-predicts-25-percent-of-people-will-spend-at-least-one-hour-per-day-in-the-metaverse-by-2026\nhttps://www.mckinsey.com/business-functions/growth-marketing-and-sales/our-insights/value-creation-in-the-metaverse?stcr=378CC4A6B8484C309CBA1AED40EEC786&cid=other-eml-alt-mip-mck&hlkid=f9132bba8e2e4ffd98110ae8218ee1f9&hctky=13588526&hdpid=2708fc59-438d-4169-8874-81a6db2733ca",
        "ngay_dang": "16/08/2022",
        "ngay_crawl": "2025-09-09 20:00:45"
    }
]