[
    {
        "id": 1,
        "title": "Việt Nam và Hoa Kỳ tăng cường thúc đẩy thương mại nông sản",
        "url": "http://www.saigontel.vn/vi/tin-tuc/tin-tuc/1666-viet-nam-va-hoa-ky-tang-cuong-thuc-day-thuong-mai-nong-san.html",
        "content": "Thứ trưởng Bộ Nông nghiệp-Phát triển Nông thôn Lê Quốc Doanh khẳng định những năm qua quan hệ Việt Nam-Hoa Kỳ liên tục phát triển trên nhiều lĩnh vực, trong đó có nông nghiệp, thương mại nông sản\nThứ trưởng Bộ Nông nghiệp và Phát triển nông thôn Lê Quốc Doanh. (Ảnh: Lâm Khánh/TTXVN)\nTừ ngày 24-29/2, đoàn công tác của Bộ Nông nghiệp và Phát triển Nông thôn do Thứ trưởng Lê Quốc Doanh làm Trưởng đoàn có chuyến thăm và làm việc tại Hoa Kỳ nhằm tăng cường hoạt động hợp tác và trao đổi thương mại nông sản giữa hai nước.\nĐây là chuyến công tác nằm trong kế hoạch hành động hướng tới cán cân thương mại hài hòa và bền vững giữa Việt Nam và Hoa Kỳ.\nTrong khuôn khổ chuyến thăm, ngày 24/2, đoàn công tác của Bộ Nông nghiệp và Phát triển Nông thôn cùng các doanh nghiệp đầu ngành trong lĩnh vực kinh doanh nông lâm sản và các nhà nhập khẩu lớn trong lĩnh vực sản phẩm chăn nuôi, rau quả, lâm sản, chế biến thực phẩm, thức ăn chăn nuôi của Việt Nam đã tham dự buổi tọa đàm bàn tròn với các hiệp hội ngành hàng và các doanh nghiệp Hoa Kỳ được tổ chức tại thủ đô Washington nhằm thúc đẩy thương mại nông sản giữa hai nước, góp phần vào mục tiêu tăng trưởng thương mại hai chiều giữa Việt Nam và Hoa Kỳ.\nPhát biểu tại buổi tọa đàm, Thứ trưởng Bộ Nông nghiệp và Phát triển Nông thôn Lê Quốc Doanh khẳng định trong những năm qua quan hệ giữa Việt Nam và Hoa Kỳ đã liên tục phát triển trên nhiều lĩnh vực, trong đó có hợp tác trong lĩnh vực nông nghiệp và thương mại nông sản.\nHoa Kỳ là đối tác thương mại lớn thứ 3 của Việt Nam trên toàn cầu, trong khi Việt Nam cũng trở thành thị trường xuất khẩu lớn thứ 27 và là đối tác thương mại lớn thứ 16 của Hoa Kỳ.\nTheo Thứ trưởng Lê Quốc Doanh, hiện vẫn còn tiềm năng rất lớn trong hợp tác trong lĩnh vực thương mại nông sản giữa hai nước và quan hệ thương mại giữa hai nước không phải là cạnh tranh mà là bổ trợ lẫn nhau.\nHoa Kỳ hiện là nước đứng đầu thế giới về sản xuất nông nghiệp hiện đại, trong khi Việt Nam đang trong quá trình cơ cấu lại sản xuất nông nghiệp hiệu quả hơn và gắn với nhu cầu thị trường.\nViệt Nam có thế mạnh với nhiều sản phẩm đặc trưng của vùng nhiệt đới như hoa quả và có nguồn hải sản chất lượng cao. Chính vì vậy, đây là cơ hội lớn để doanh nghiệp hai bên tận dụng và thúc đẩy phát triển thương mại nông sản giữa hai nước.\nTại buổi tọa đàm, đại diện các hiệp hội ngành hàng của Hoa Kỳ đánh giá cao sáng kiến của Việt Nam khi tổ chức buổi tọa đàm và tổ chức cho đoàn doanh nghiệp Việt Nam sang Hoa Kỳ để tìm kiếm các đối tác và các nhà xuất khẩu nông sản có uy tín của nước này để nhập khẩu các mặt hàng nông sản có chất lượng cao và là thế mạnh của Hoa Kỳ như ngũ cốc, lúa mỳ, ngô, đậu tương…; đồng thời bày tỏ sẵn sàng giúp đỡ cũng như tạo mọi điều kiện thuận lợi cho các doanh nghiệp Việt Nam trong thời gian tới.\nNgoài ra, hai bên đã trao đổi thông tin, tiềm năng hợp tác và nêu những vướng mắc, khó khăn mà doanh nghiệp hai nước đang gặp phải như vấn đề về giá sản phẩm nhập khẩu cao, mức thuế quan cao, sản phẩm lúa mỳ có lẫn hạt cỏ dại, thương mại với Hoa Kỳ phải qua trung gian, mất nhiều thời gian vận chuyển, sản phẩm ngô của Hoa Kỳ có độ ẩm cao nên khó bảo quản…\nNhằm giải quyết những vướng mắc hiện nay của doanh nghiệp hai nước, Thứ trưởng Lê Quốc Doanh đề nghị các doanh nghiệp hai nước tìm hiểu kỹ các quy định thị trường, quy định xuất nhập khẩu vào thị trường của mỗi nước, thường xuyên cập nhật thông tin đối tác, tham gia các hoạt động xúc tiến thương mại của Bộ Nông nghiệp và Phát triển Nông thôn, Bộ Nông nghiệp Hoa Kỳ để kết nối, giao thương với các đối tác lớn, có uy tín, nhằm đem lại kết quả và hài hòa lợi ích hai bên như mong muốn.\nHai bên cũng nên thường xuyên phản ánh các thông tin về những khó khăn vướng mắc, kiến nghị tới Bộ Nông nghiệp và Phát triển Nông thôn, Bộ Nông nghiệp Hoa Kỳ để có giải pháp, tạo điều kiện thuận lợi cho hoạt động thương mại nông lâm thủy sản giữa hai nước, đặc biệt là xuất khẩu các sản phẩm nông lâm thủy sản có thế mạnh của Hoa Kỳ, có tính chất bổ sung sang thị trường Việt Nam.\nTham dự buổi tọa đàm, ông Nguyễn Quốc Toản, Cục trưởng Cục Chế biến và Phát triển thị trường nông sản, Bộ Nông nghiệp và Phát triển Nông thôn, cho biết Việt Nam luôn coi Hoa Kỳ là đối tác hàng đầu và coi trọng cân bằng cán cân thương mại của hai nước.\nMặc dù Việt Nam đã trở thành một nước xuất khẩu nông sản đứng hai trong Hiệp hội các quốc gia Đông Nam Á (ASEAN) và đứng thứ năm trên thế giới, song Việt Nam vẫn có nhu cầu nhập khẩu các nguồn nguyên liệu, đặc biệt là các nguồn nguyên liệu chất lượng cao của Hoa Kỳ và trình độ khoa học công nghệ đáp ứng cho công nghiệp chế biến nông sản của Việt Nam. Đây cũng là chỉ đạo gần đây nhất của Thủ tướng Chính phủ về nâng cao năng lực về chế biến nông sản và cơ giới hóa trong nông nghiệp.\nSau hoạt động tại Thủ đô Washington, đoàn công tác của Bộ Nông nghiệp và Phát triển Nông thôn tiếp tục có nhiều hoạt động tại các bang khác của Hoa Kỳ như Iowa và Nebraska./.",
        "ngay_dang": "Viết bởiNgô Thị Lam Vân- Thứ ba, 25 Tháng 2 2020",
        "ngay_crawl": "2025-09-12 17:17:23"
    },
    {
        "id": 2,
        "title": "Loại bỏ những rào cản đối hoạt động đầu tư của Việt Nam ra nước ngoài",
        "url": "http://www.saigontel.vn/vi/tin-tuc/tin-tuc/1665-loai-bo-nhung-rao-can-doi-hoat-dong-dau-tu-cua-viet-nam-ra-nuoc-ngoai.html",
        "content": "Hoạt động đầu tư ra nước ngoài của các doanh nghiệp Việt Nam hiện nay vẫn tiềm ẩn nhiều rủi ro, thách thức. Để nâng cao hiệu quả hoạt động đầu tư ra nước ngoài của doanh nghiệp Việt Nam, cần có những công cụ hướng dẫn doanh nghiệp giải quyết hiệu quả các khó khăn, vướng mắc gặp phải trong quá trình đầu tư ra nước ngoài.\nNhiều tập đoàn, tổng công ty, doanh nghiệp có vốn đăng ký đầu tư ra nước ngoài đã vượt ngưỡng 1 tỷ USD\nKết quả tích cực từ chính sách thông thoáng\nVốn đầu tư trực tiếp ra nước ngoài của các doanh nghiệp (DN) Việt Nam trải qua các giai đoạn thăng trầm, bắt đầu manh nha những dự án đầu tiên từ những năm 1989, sau đó tăng trưởng mạnh về số dự án và vốn đăng ký từ khi Chính phủ ban hành Nghị định số 78/2006/NĐ-CP ngày 9/8/2006 quy định về đầu tư trực tiếp ra nước ngoài.\nTuy nhiên, sự khởi sắc của hoạt động đầu tư ra nước ngoài của DN Việt Nam thực sự bắt đầu nhờ nỗ lực chuẩn hóa thủ tục đầu tư gắn với hoàn thiện hành lang pháp lý phù hợp với bối cảnh mới. Thực tế cho thấy, kể từ khi Nghị định số 83/2015/NĐ-CP của Chính phủ hướng dẫn về đầu tư ra nước ngoài được ban hành, việc mở rộng phạm vi đầu tư, kinh doanh ở nước ngoài của DN trong nước đã được tạo điều kiện thuận lợi hơn.\nNgoài ra, Thông tư số 03/2018/TT-BKHĐT do Bộ Kế hoạch và Đầu tư ban hành  ngày 17/10/2018 hướng dẫn và ban hành mẫu văn bản thực hiện thủ tục đầu tư ra nước ngoài cũng đã góp phần chuẩn hóa thủ tục pháp lý cho hoạt động đầu tư ra nước ngoài, vừa tạo môi trường thông thoáng, vừa giúp cơ quan quản lý nhà nước tăng cường hiệu lực quản lý với các dự án ngoài lãnh thổ Việt Nam...\nNhờ đó, đến nay, hoạt động đầu tư ra nước ngoài của Việt Nam đã tạo được những dấu ấn nhất định. Thống kê cho thấy, lũy kế từ năm 1989 đến nay, Việt Nam đã đầu tư ra nước ngoài hơn 22 tỷ USD với các lĩnh vực thế mạnh của Việt Nam là nông nghiệp, lâm nghiệp, năng lượng và viễn thông. Trong đó, các nước như Lào, Campuchia và Myanmar chiếm gần 40% tổng vốn đầu tư ra nước ngoài của DN Việt Nam.\nNhiều tập đoàn, tổng công ty, DN có vốn đăng ký đầu tư ra nước ngoài đã vượt ngưỡng 1 tỷ USD như: Tập đoàn Dầu khí Việt Nam, Tập đoàn Viễn thông Quân đội (Viettel), Công ty Cổ phần Hoàng Anh - Gia Lai....\nRiêng năm 2019, tổng vốn đầu tư ra nước ngoài cấp mới và tăng thêm của Việt Nam đạt 508,14 triệu USD; trong đó, có 164 dự án được cấp Giấy chứng nhận đăng ký đầu tư mới, với tổng vốn đầu tư bên Việt Nam đạt 403,15 triệu USD. Bên cạnh đó, có 29 lượt dự án điều chỉnh vốn đầu tư với vốn đầu tư Việt Nam tăng thêm gần 105 triệu USD.\nNhững rủi ro, thách thức cần được khắc phục\nBên cạnh những đóng góp tích cực vào phát triển kinh tế - xã hội cho Việt Nam, cho các quốc gia và cộng đồng tiếp nhận đầu tư thì đầu tư ra nước ngoài của các DN Việt Nam hiện nay vẫn tiềm ẩn nhiều rủi ro, thách thức. Cụ thể, những khác biệt về văn hóa, pháp luật, môi trường giữa Việt Nam và các quốc gia tiếp nhận đầu tư này đã dẫn đến các tranh chấp ngoài mong muốn, ảnh hưởng đến việc thực hiện dự án, quyền và lợi ích của người dân địa phương cũng như hình ảnh của nhà đầu tư Việt Nam trong khu vực và trên thế giới.\nNăng lực của DN Việt Nam vẫn còn yếu. Theo các chuyên gia kinh tế, nguyên nhân chủ quan dẫn đến kết quả hoạt động đầu tư ra nước ngoài của DN Việt Nam khi đầu tư ra nước ngoài chưa đạt như kỳ vọng là do khả năng dự báo thị trường, năng lực quản lý, năng lực tài chính vẫn còn nhiều hạn chế. Bên cạnh đó, nhiều DN Việt Nam ra nước ngoài kinh doanh nhưng hoạt động còn mang tính tự phát, do đó cũng rất dễ xảy ra tranh chấp và hiệu quả đầu tư không cao.\nTrong thời gian tới, nhằm tăng cường và nâng cao hiệu quả hoạt động đầu tư ra nước ngoài của DN Việt Nam, về phía cơ quan quản lý nhà nước, một số vấn đề cần chú trọng thực hiện gồm: Tiếp tục hoàn thiện khuôn khổ pháp lý về liên quan đến hoạt động đầu tư ra nước ngoài của DN Việt Nam theo hướng tiệm cận dần với các thông lệ, pháp luật quốc tế, qua đó tạo điều kiện thuận lợi cho DN Việt Nam trong quá trình đầu tư ra nước ngoài; Tăng cường mở rộng hợp tác quốc tế, ký kết các hiệp định đầu tư song phương, đa phương nhằm bảo vệ các DN, gỡ bỏ các rào cản khi đầu tư trực tiếp ra nước ngoài…\nQuan trọng hơn, cơ quan quản lý cần có những công cụ hướng dẫn DN giải quyết hiệu quả các khó khăn, vướng mắc, rủi ro gặp phải trong quá trình đầu tư ra nước ngoài; Kịp thời nắm bắt, xử lý các vướng mắc, khó khăn của DN đầu tư ra nước ngoài; Hướng dẫn cung cấp thông tin tổng thể về quy trình đầu tư ra nước ngoài từ Việt Nam đến nước nhận đầu tư; Chú trọng hỗ trợ về mặt pháp lý, chủ động phối hợp cùng DN tham gia xử lý các vấn đề phát sinh, các tranh chấp trong quá trình đầu tư tại nước sở tại.\nVề phía DN, cần chủ động tìm hiểu, tuân thủ pháp luật nước sở tại, luật pháp quốc tế và các chính sách, pháp luật có liên quan khác. DN phải có ý thức bảo vệ môi trường sống nơi sở tại, cần đảm bảo lợi ích hài hòa cho người dân địa phương, tạo công ăn việc làm và tích cực các hoạt động từ thiện, xóa đói giảm nghèo đối với quốc gia nhận đầu tư. Bên cạnh đó, DN tiếp tục nâng cao năng lực dự báo thị trường, năng lực tài chính; Xây dựng chiến lược kinh doanh, chiến lược sản phẩm, thương hiệu để từng bước nâng cao năng lực quản trị; Cần có các khảo sát, nghiên cứu kỹ lưỡng về cơ chế đầu tư, tiềm năng thị trường, triển vọng lợi nhuận… trước khi đưa ra các quyết định đầu tư.",
        "ngay_dang": "Viết bởiNgô Thị Lam Vân- Thứ ba, 25 Tháng 2 2020",
        "ngay_crawl": "2025-09-12 17:17:24"
    },
    {
        "id": 3,
        "title": "Tổng kim ngạch xuất, nhập khẩu hàng hóa nửa đầu tháng 2/2020 đạt 19,23 tỷ USD",
        "url": "http://www.saigontel.vn/vi/tin-tuc/tin-tuc/1664-tong-kim-ngach-xuat-nhap-khau-hang-hoa-nua-dau-thang-22020-dat-1923-ty-usd.html",
        "content": "Theo thống kê sơ bộ của Tổng cục Hải quan, tổng trị giá xuất nhập khẩu hàng hóa của Việt Nam trong 15 ngày đầu tháng 2 đạt 19,23 tỷ USD, tăng 32% so với nửa cuối tháng 1/2020 và tăng nhẹ 3,3% so với cùng kỳ năm 2019.\nCụ thể, trong 15 ngày đầu tháng 2/2020, xuất khẩu của Việt Nam đạt trị giá 9,6 tỷ USD, tăng 30% so với nửa cuối tháng 1/2020. Trong đó, doanh nghiệp có vốn đầu tư trực tiếp nước ngoài (FDI) đạt 6,78 tỷ USD.\nLuỹ kế đến hết ngày 15/2, kim ngạch xuất khẩu của Việt Nam đạt 27,86 tỷ USD, tăng 5,4% so với cùng kỳ năm 2019. Trong đó, khối doanh nghiệp FDI chiếm 18,5 tỷ USD.\nĐặc biệt, xuất khẩu ngành dệt may và giày dép có mức tăng trưởng đột biến, tăng 44,64% so với cùng kỳ với kim ngạch đạt hơn 3 tỷ USD. Kim ngạch này cao hơn nhiều so với kim ngạch xuất khẩu bình quân các tháng Tết của 3 năm trước đó (khoảng hơn 2 tỷ USD).\nLý giải về điều này, theo  đánh giá của các nhà phân tích nguyên nhân chính xuất phát từ việc một số công ty đa quốc gia đã tăng công suất tại các nhà máy tại Việt Nam nhằm bổ sung cho đơn hàng dệt may, giày dép bị thiếu hụt do các nhà máy ở Trung Quốc bị đóng cửa.\nXuất khẩu mặt hàng điện tử có mức tăng trưởng khiêm tốn, khoảng 2% so với cùng kỳ do đây là thời điểm trước khi ra mắt các dòng sản phẩm mới nên nhu cầu bị suy giảm.\nỞ chiều nhập khẩu, kim ngạch trong 15 ngày đầu tháng 2 đạt 9,62 tỷ USD, tăng 33,7% so với nửa cuối tháng 1. Trong đó, kim ngạch nhập khẩu của doanh nghiệp FDI đạt 5,8 tỷ USD.\nLuỹ kế đến hết ngày 15/2, kim ngạch nhập khẩu của Việt Nam đạt 28,27 tỷ USD, giảm 1,3% so với cùng kỳ năm ngoái. Trong đó, trị giá nhập khẩu của khối doanh nghiệp FDI đạt 16,5%.\nCụ thể, nhập khẩu của khối doanh nghiệp FDI tăng 16,01% so với cùng kỳ năm 2019, trong khi khu vực kinh tế trong nước tăng 12,64%, cao hơn nhiều so với năm 2019 (tăng trưởng 2 khu vực này trong năm 2019 đạt khoảng 4-5%).\nTác động rõ ràng nhất của dịch nCoV đến  hoạt động nhập khẩu là sự sụt giảm mạnh của các mặt hàng nguyên vật liệu đầu vào như phân bón, nguyên liệu dược phẩm, nguyên liệu thuốc lá và các mặt hàng nông sản (giảm hơn 30% so với Tết 2019); tình hình nhập khẩu nguyên liệu dệt may (bông, sợi dệt, vải các loại) có diễn biến trái chiều khi bông và sợi dệt giảm nhẹ (-5,50%), trong khi nhập khẩu vải các loại tăng mạnh (11,35%); Nhập khẩu mặt hàng điện tử, điện thoại và máy móc thiết bị duy trì mức tăng trưởng tốt. Đáng chú ý, nhập khẩu mặt hàng điện tử và đồ gia dụng ở Kỳ 1 tháng 2 còn có xu hướng tăng so với Kỳ 1 tháng 1.\nNhư vậy, trái với lo ngại, tác động ban đầu của dịch nCoV đối với hoạt động thương mại của Việt Nam là chưa nhiều, chủ yếu là tác động đến các mặt hàng được vận chuyển thông qua đường biên giới trên bộ như nông sản hoặc nguyên vật liệu đầu vào (chiếm tỷ trọng thấp). Tuy nhiên, các chuyên gia kinh tế cũng đưa ra cảnh báo, trong thời gian tới, hoạt động xuất, nhập khẩu sẽ gặp nhiều thách thức do các nhà máy sản xuất của Trung Quốc vẫn chưa hoạt động trở lại hoặc hoạt động cầm trừng dẫn đến nguồn cung nhiều khả năng sẽ bị gián đoạn.",
        "ngay_dang": "Viết bởiNgô Thị Lam Vân- Thứ ba, 25 Tháng 2 2020",
        "ngay_crawl": "2025-09-12 17:17:25"
    },
    {
        "id": 4,
        "title": "Tp.HCM phê duyệt nhiệm vụ quy hoạch Khu đô thị Tây Bắc quy mô hơn 6.000ha",
        "url": "http://www.saigontel.vn/vi/tin-tuc/tin-tuc/1663-tphcm-phe-duyet-nhiem-vu-quy-hoach-khu-do-thi-tay-bac-quy-mo-hon-6000ha.html",
        "content": "Theo đề xuất của Sở Quy hoạch - Kiến trúc TPHCM, UBND TP vừa ban hành Quyết định 351/QĐ-UBND TPHCM phê duyệt điều chỉnh nhiệm vụ quy hoạch phân khu tỷ lệ 1/5000 khu đô thị Tây Bắc Tp.HCM.\nCụ thể, toàn bộ Khu đô thị Tây Bắc bao gồm xã Tân Thới Nhì (huyện Hóc Môn); các xã Tân An Hội, Phước Hiệp, Tân Phú Trung, Tân Thông Hội và thị trấn Củ Chi (huyện Củ Chi) được giới hạn bởi quốc lộ 22, Khu Liên hiệp Xử lý chất thải rắn Tây Bắc, kênh An Hạ, kênh Thầy Cai, nằm trong khu vực điều chỉnh. Tổng diện tích khu đô thị Tây Bắc được điều chỉnh hơn 6.000ha.\nPhó Chủ tịch UBND Tp.HCM Võ Văn Hoan chỉ đạo, cần tư vấn nghiên cứu điều chỉnh nhiệm vụ quy hoạch phân khu tỷ lệ 1/5000 Khu đô thị Tây Bắc, nghiên cứu những ý kiến đóng góp hợp lý của UBND huyện Củ Chi, của người dân Củ Chi trong chỉnh trang các khu dân cư hiện hữu. Tại các khu vực mà dân cư phải di dời để xây dựng mới các khu chức năng đô thị theo quy hoạch, cần ưu tiên bố trí tái định cư tại chỗ.\nBên cạnh chính sách đền bù, giải phóng mặt bằng phù hợp, khuyến khích người dân đồng thuận hợp tác, đầu tư vào những dự án chỉnh trang đô thị, để vừa khai thác hiệu quả sử dụng đất, dần thay đổi bộ mặt đô thị vừa cải thiện, nâng cao điều kiện, môi trường sống cho cộng đồng dân cư. Chỉnh trang các khu dân cư hiện hữu theo hướng tránh xáo trộn lớn đến cuộc sống của cộng đồng dân cư.\nĐối với các khu ở mới, sẽ được quy hoạch hiện đại với đầy đủ chức năng, đảm bảo đồng bộ hạ tầng xã hội, kỹ thuật nhằm thu hút các nhà đầu tư cũng như đảm bảo cho khu đô thị phát triển bền vững. Ưu tiên bố trí các công trình cao tầng của các khu dân cư mới dọc trục giao thông chính, có động lực phát triển, như trục song hành quốc lộ 22, dọc tuyến metro số 2 (Bến Thành - Tham Lương - Củ Chi)… không gian kiến trúc thấp dần về phía sau. Tập trung bố trí cụm công trình có chức năng dịch vụ, thương mại (cao tầng) tại các khu vực trung tâm khu đô thị, nhà ga của tuyến metro số 2.\nKhu vực tiếp giáp kênh Đông và các kênh 5, 6, 7, 8 sẽ phát huy ưu thế địa hình sông nước, tạo không gian mở, hài hòa với cảnh quan chung của khu vực. Phát triển mô hình nhà vườn với mật độ xây dựng thấp. Các công trình cao tầng được bố trí lùi dần ra phía sau, theo nguyên tắc cao dần về phía bên trong so với khu vực gần kênh, rạch.\nNgoài ra, dọc các tuyến kênh này sẽ nghiên cứu đề xuất xây dựng các tuyến đường giao thông ven sông, kênh, rạch… có kết nối với mạng giao thông toàn khu vực, phù hợp với cảnh quan bờ sông, kênh.\nKhu đô thị Tây Bắc sẽ là một trung tâm cấp thành phố với các chức năng: dịch vụ, thương mại, y tế, văn hóa, giáo dục đào tạo, thể dục thể thao và nghỉ dưỡng vui chơi giải trí. Dân số quy hoạch đến năm 2025 là 300.000 người. Đây là con số không đổi so với quy hoạch hiện hữu (đang được nghiên cứu điều chỉnh).\nVề chức năng phát triển công nghiệp vẫn được duy trì ở Khu đô thị Tây Bắc TPHCM, nhưng được điều chỉnh theo hướng là công nghiệp sạch, ứng dụng công nghệ, kỹ thuật cao, dịch vụ công nghệ cao. Ngay cả Khu công nghiệp Tân Phú Trung hiện hữu cũng phải chuyển theo hướng đó. Đồng thời, tiếp tục triển khai dự án khu đô thị đại học quốc tế nhằm san sẻ áp lực lên hệ thống hạ tầng kỹ thuật, hạ tầng xã hội cho khu vực trung tâm hiện hữu của thành phố.",
        "ngay_dang": "Viết bởiNgô Thị Lam Vân- Thứ ba, 25 Tháng 2 2020",
        "ngay_crawl": "2025-09-12 17:17:26"
    },
    {
        "id": 5,
        "title": "Tp.HCM đang hoàn thiện quy hoạch đường bờ sông Sài Gòn, đưa quy hoạch Cần Giờ, khu đô thị phía Đông thành đề án riêng",
        "url": "http://www.saigontel.vn/vi/tin-tuc/tin-tuc/1662-tphcm-dang-hoan-thien-quy-hoach-duong-bo-song-sai-gon-dua-quy-hoach-can-gio-khu-do-thi-phia-dong-thanh-de-an-rieng.html",
        "content": "Ông Nguyễn Thành Phong, Chủ tịch UBND Tp.HCM cho biết TP hiện có khoảng 8,9 triêu dân, tuy nhiên con số thực tế là hơn 13 triệu người. Việc ngân sách Trung ương chỉ tính mức chi để phục vụ 8,9 triệu dân sẽ là trở ngại cho Tp.HCM cho việc đầu tư phát triển.\nTrong cuộc họp mới đây, ông Nguyễn Thành Phong thông tin thành phố đang thực hiện chiến lược điều chỉnh lại quy hoạch tổng thể cả về kinh tế xã hội và hạ tầng bởi quy hoạch hiện nay đã lạc hậu. Trong đó, thành phố sẽ tính tới quy mô dân số thực tế trên toàn địa bàn.\nHiện TP đã giao cho Sở Quy hoạch Kiến trúc hoàn thiện quy hoạch đường bờ sông Sài Gòn để tận dụng được tiềm năng của khu vực ven sông. Ngoài ra, thành phố đang có những chỉ đạo cụ thể để biến quy hoạch mới huyện Cần Giờ, khu đô thị phía đông thành phố thành những đề án và bổ sung vào quy hoạch chung toàn thành phố. Trong đó, Chủ tịch TP Nguyễn Thành Phong sẽ là Trưởng ban chỉ đạo xây dựng phát triển khu đô thị phía Đông (ban này sẽ đi vào hoạt động vào quý 2/2020).\nBên cạnh đó, quy hoạch phân khu của Bình Quới - Thanh Đa và khu tây bắc thành phố cũng có sự điều chỉnh và cập nhật vào bản đồ chung. Thành ủy và UBND TP.HCM đã thống nhất giao sở Quy hoạch Kiến trúc hoàn thành vào cuối năm 2020.\nNói về những khó khăn trong việc điều chỉnh quy hoạch, ông Nguyễn Thành Phong cho rằng, đó là thách thức về dân số trên địa bàn TP. Theo con số thống kê của chính quyền, TP hiện có khoảng 8,9 triệu dân, tuy nhiên con số thực tế là hơn 13 triệu người. Việc ngân sách Trung ương chỉ tính mức chi để phục vụ 8,9 triệu dân sẽ là trở ngại cho Tp.HCM cho việc đầu tư phát triển.\nTrong lần điều chỉnh quy hoạch này, TP sẽ phải tính đến vấn đề dân số, nếu có thể tổ chức hệ thống giao thông tới các khu vực lân cận, người lao động có thể đi về trong ngày, giảm thiểu gánh nặng về dân số cho Tp.HCM. Bên cạnh đó, TP khuyến khích các nhà đầu tư áp dụng khoa học công nghệ để giảm nhân công trong các khu công nghiệp.",
        "ngay_dang": "Viết bởiNgô Thị Lam Vân- Thứ ba, 25 Tháng 2 2020",
        "ngay_crawl": "2025-09-12 17:17:26"
    },
    {
        "id": 6,
        "title": "Công bố các dự án nhà ở và thị trường bất động sản quý 4 năm 2019",
        "url": "http://www.saigontel.vn/vi/tin-tuc/tin-tuc/1660-cong-bo-cac-du-an-nha-o-va-thi-truong-bat-dong-san-quy-4-nam-2019.html",
        "content": "Thông tin từ Bộ Xây dựng cho biết trong quý 4 năm 2019, trên cả nước có 55 dự án bất động sản được Cục Giám định nhà nước về chất lượng công trình xây dựng chấp thuận nghiệm thu đưa vào sử dụng.\nTrong quý 4 năm 2019 có 36 dự án phát triển nhà ở với 6.168 căn hộ hoàn thành. (Ảnh: Hùng Võ/Vietnam+)\nCục Quản lý nhà và thị trường bất động sản - Bộ Xây dựng vừa công bố thông tin về tình hình nhà ở và thị trường bất động sản quý 4/2019. Đây là lần thứ hai, Bộ Xây dựng thực hiện quyết định công bố thông tin về nhà ở và thị trường bất động sản định kỳ hàng quý, hàng năm trên phạm vi cả nước.\nTheo đó, qua tổng hợp từ 29/63 Ủy ban Nhân dân có báo cáo, trong quý 4 năm 2019 có 62 dự án phát triển nhà ở với 11.365 căn hộ được cấp phép; 461 dự án với 186.761 căn hộ đang triển khai xây dựng.\nĐến nay đã có 36 dự án phát triển nhà ở với 6.168 căn hộ hoàn thành.\nĐối với dự án du lịch nghỉ dưỡng, có 23 dự án với 7.147 căn hộ du lịch và 1.926 biệt thự du lịch được cấp phép; 96 dự án với 16.827 căn hộ du lịch và 5.705 biệt thự du lịch đang triển khai xây dựng.\nCó 18.329 giao dịch bất động sản, bao gồm căn hộ chung cư, nhà ở riêng lẻ, đất nền chuyển nhượng, văn phòng cho thuê, căn hộ du lịch (condotel), biệt thự du lịch (resort/villa), văn phòng kết hợp lưu trú (officetel) đã thực hiện thành công.\nTrong số đó, riêng thành phố Hà Nội có 3.099 giao dịch thành công. Số lượng giao dịch thành công ở Thành phố Hồ Chí Minh là 5.142 giao dịch.\nTương tự, nguồn cung nhà ở, bao gồm số lượng chung cư, nhà ở riêng lẻ, đất nền được tổng hợp từ 29/63 Ủy ban Nhân dân có báo cáo cho thấy có 47 dự án với 11.714 căn hộ đủ điều kiện bán nhà ở hình thành trong tương lai được Sở Xây dựng có văn bản thông báo đủ điều kiện.\nẢnh minh họa. (Nguồn: TTXVN)\nTheo đánh giá của Cục Quản lý nhà và thị trường bất động sản , trong quý 4 năm 2019, giá bất động sản tại thành phố Hà Nội và Thành phố Hồ Chí Minh có biến động, tuy nhiên mức độ biến động không lớn.\nCụ thể, tại thành phố Hà Nội, giá căn hộ chung cư tăng khoảng 0,23% so với quý III/2019 (trong đó đối với phân khúc căn hộ cao cấp giá tăng khoảng 0,03%, căn hộ trung cấp giá tăng khoảng 0,30%, căn hộ bình dân giá tăng khoảng 0,53%). Giá nhà ở riêng lẻ giá tăng khoảng 0,51%.\nTại Thành phố Hồ Chí Minh, giá căn hộ chung cư tăng khoảng 1,01% so với quý III/2019 (trong đó đối với phân khúc căn hộ cao cấp giá tăng khoảng 0,74%, căn hộ trung cấp giá tăng khoảng 1,01%, căn hộ bình dân giá tăng khoảng 1,30%). Giá nhà ở riêng lẻ tăng khoảng 0,74%.\nTrong quý 4, số lượng bất động sản được Cục Quản lý hoạt động xây dựng thẩm định, với nhà ở là 8.555 căn; căn hộ du lịch có 506 căn. Riêng biệt thự du lịch và văn phòng kết hợp lưu trú (officetel), không có căn nào được thẩm định.\nTrên cơ sở kiểm tra, rà soát, có 55 dự án đã được Cục Giám định nhà nước về chất lượng công trình xây dựng chấp thuận nghiệm thu đưa vào sử dụng; trong đó loại hình nhà ở có 29.679 căn, căn hộ du lịch 2.451 căn, officetel có 2.882 căn./.",
        "ngay_dang": "Viết bởiNgô Thị Lam Vân- Thứ hai, 24 Tháng 2 2020",
        "ngay_crawl": "2025-09-12 17:17:27"
    },
    {
        "id": 7,
        "title": "[Infographics] Dự báo tác động của EVFTA đến tăng trưởng ngành hàng",
        "url": "http://www.saigontel.vn/vi/tin-tuc/tin-tuc/1659-infographics-du-bao-tac-dong-cua-evfta-den-tang-truong-nganh-hang.html",
        "content": "",
        "ngay_dang": "Viết bởiNgô Thị Lam Vân- Thứ hai, 24 Tháng 2 2020",
        "ngay_crawl": "2025-09-12 17:17:28"
    },
    {
        "id": 8,
        "title": "Đồng Nai: Sẽ đấu giá 5 khu đất ở huyện Long Thành với giá khởi điểm 550 tỷ đồng",
        "url": "http://www.saigontel.vn/vi/tin-tuc/tin-tuc/1658-dong-nai-se-dau-gia-5-khu-dat-o-huyen-long-thanh-voi-gia-khoi-diem-550-ty-dong.html",
        "content": "Theo kế hoạch của UBND tỉnh Đồng Nai, trong năm 2020, sẽ tiến hành đấu giá khoảng 5 khu đất tại huyện Long Thành để lấy vốn đầu tư cho các công trình hạ tầng kỹ thuật trên địa bàn tỉnh.\nCác khu đất ở huyện Long Thành đưa ra đấu giá có tổng diện tích 82,2 ha và đều là những khu vực đắc địa, gần đường lớn rất thuận lợi cho phát triển thương mại, dịch vụ và xây dựng khu dân cư.\nGiá khởi điểm của 5 khu đất trên là gần 550 tỷ đồng. Những khu đất trên đều được UBND tỉnh quy hoạch là đất ở, đất thương mại dịch vụ. Doanh nghiệp, cá nhân đấu giá thành công các khu đất trên có thể triển khai nhanh các dự án vì hầu hết đã có sẵn đất sạch và quy hoạch xây dựng chi tiết 1/500. Các khu đất dự kiến đấu giá nằm trên địa bàn xã Long Đức, Lộc An, Long An, Phước Bình, Bình Sơn.\nTheo các chuyên gia trên lĩnh vực bất động sản, những khu đất trên có lợi thế lớn là nằm gần Cảng hàng không quốc tế Long Thành, giao thông thuận lợi nên nhiều nhà đầu tư rất muốn mua. Do đó, giá bán có thể cao gấp 1,5-2 lần so với giá khởi điểm.\nTheo Quyết định 4383/QĐ-UBND của UBND tỉnh Đồng Nai về phê duyệt kế hoạch sử dụng đất năm 2020 của huyện Long Thành, trên địa bàn huyện có 10 khu đất sẽ được đấu giá với tổng diện tích 249 ha. Trong đó, có 4 khu đất quy hoạch khu dân cư gồm: Khu dân cư thuộc xã An Phước, Long Đức rộng hơn 186 ha; 2 khu dân cư ở xã Long Đức có diện tích lần lượt là 22 ha và 4 ha; Khu dân cư xã Lộc An gần 2 ha. Còn lại các khu đất khác nằm tại thị trấn Long Thành, các xã Long An, Bình An, Phước Bình.\nNăm 2019, huyện Long Thành có 2 khu đất \"vàng\" đấu giá được gần 4,8 ngàn tỷ đồng. Năm 2020, huyện Long Thành tiếp tục là địa phương có nhiều khu đất công có diện tích lớn và vị trí đẹp đưa ra đấu giá.\nTheo kế hoạch, dự kiến năm 2020, Đồng Nai tiếp tục đưa ra đấu giá khoảng 20 khu “đất vàng” ở các huyện Long Thành, Thống Nhất, Trảng Bom, Định Quán và 2 thành phố là Long Khánh và Biên Hòa. Số tiền thu được từ việc bán đất sẽ đầu tư vào các dự án quan trọng của tỉnh. Tổng diện tích của các khu đất sẽ đưa ra đấu giá năm 2020 là hơn 276 ha và giá khởi điểm là 2.352 tỷ đồng. Tuy nhiên, đất đai Đồng Nai đang có giá nên nếu đấu giá thành công có thể thu về số tiền gấp 1,5-2 lần so với giá khởi điểm.\nKhu đất có diện tích lớn nhất là hơn 93 ha nằm trên địa bàn thị trấn Dầu Giây và xã Hưng Lộc (huyện Thống Nhất). Giá khởi điểm hơn 860 tỷ đồng, được quy hoạch là đất dự án khu dân cư. Với lợi thế nằm gần đường cao tốc TP.Hồ Chí Minh - Long Thành - Dầu Giây và tới đây là đường cao tốc Dầu Giây - Liên Khương, Dầu Giây - Phan Thiết, dự án này được nhiều doanh nghiệp muốn mua để đầu tư xây dựng.\nThửa đất có diện tích lớn thứ hai dự kiến sẽ đấu giá trong tháng 9/2020 nằm ở 2 xã Bình Sơn - Lộc An (huyện Long Thành), rộng hơn 23 hécta, quy hoạch làm dự án đất ở, giá khởi điểm trên 310 tỷ đồng. Bên cạnh đó, tại 2 xã Bình Sơn - Lộc An còn có khu đất quy hoạch phát triển thương mại dịch vụ khoảng 12 ha dự tính được đấu giá trong tháng 11/2020 và giá khởi điểm là 169 tỷ đồng.",
        "ngay_dang": "Viết bởiNgô Thị Lam Vân- Thứ hai, 24 Tháng 2 2020",
        "ngay_crawl": "2025-09-12 17:17:29"
    },
    {
        "id": 9,
        "title": "Hai cây cầu trăm tỷ qua mặt hồ Linh Đàm",
        "url": "http://www.saigontel.vn/vi/tin-tuc/tin-tuc/1657-hai-cay-cau-tram-ty-qua-mat-ho-linh-dam.html",
        "content": "Dự án xây dựng hai cây cầu nối đường Nguyễn Xiển và Hoàng Liệt đi qua hồ Linh Đàm được kỳ vọng làm giảm tình trạng ùn tắc tại cửa ngõ phía nam Thủ đô.\nTuyến đường vành đai 3 đi thấp qua hồ Linh Đàm (quận Hoàng Mai, Hà Nội) được UBND TP Hà Nội phê duyệt tháng 10/2018 với tổng mức đầu tư gần 340 tỷ đồng. Trong đó, chi phí bồi thường, hỗ trợ và tái định cư gần 15 tỷ đồng, chi phí xây dựng hơn 258 tỷ đồng. Dự kiến đến cuối năm 2020, dự án sẽ hoàn thành và đưa vào sử dụng.\nDự án gồm các hạng mục: xây dựng 2 cầu đi thấp qua hồ Linh Đàm có tổng chiều dài trên 500 m, chiều rộng mỗi cầu 13 m, kết nối thông suốt đường Nguyễn Xiển và đường Hoàng Liệt.\nHai cầu thấp qua hồ Linh Đàm có tổng chiều dài trên 500 m, chiều rộng mỗi cầu 13 m. Trong đó, cầu bên trái dài gần 260 m, cầu bên phải có chiều dài 282 m. Kết cấu phần trên, sử dụng hệ dầm bê tông cốt thép dự ứng lực, bản mặt cầu bê tông cốt thép, mặt cầu bằng bê tông nhựa chặt.\nHai cây cầu thấp bắc qua hồ Linh Đàm giúp kết nối hai đường Nghiêm Xuân Yêm và đường Hoàng Liệt. Ngoài ra, còn hai cầu nhánh đi lên xuống giúp kết nối giao thông đường Nghiêm Xuân Yêm phía dưới với đường vành đai 3 trên cao và ngược lại.\nHiện nay để lưu thông từ đường Nguyễn Xiển ra Giải Phóng, Ngọc Hồi, đường cao tốc Pháp Vân, các xe phải đi lên đường trên cao hoặc vòng qua bán đảo Linh Đàm dẫn đến tình trạng quá tải, ùn tắc vào khung giờ cao điểm.\nDự án này khi hoàn thành được kỳ vọng sẽ giảm áp lực cho đường Nguyễn Hữu Thọ, đường vành đai 3 trên cao qua cửa ngõ phía nam Thủ đô.\nĐể phục vụ thi công, hàng trăm cọc ván thép được đóng xuống mặt hồ Linh Đàm tạo thành tường vây ngăn nước. Sau khi dự án hoành thành, hàng cọc này sẽ được tháo dỡ, trả lại nguyên trạng mặt nước hồ Linh Đàm như trước đó.\nMáy bơm công suất lớn chạy suốt ngày đêm để hút nước ra ngoài, đảm bảo công trường luôn khô ráo.\nĐược biết, đến nay, dự án đã thi công đạt 40% khối lượng. Trên công trường luôn duy trì 3 ca làm việc hàng ngày với khoảng 200 công nhân để kịp hoàn thành tiến độ của dự án vào tháng 9/2020.",
        "ngay_dang": "Viết bởiNgô Thị Lam Vân- Thứ hai, 24 Tháng 2 2020",
        "ngay_crawl": "2025-09-12 17:17:29"
    }
]