[
    {
        "id": 1,
        "title": "Nâng cấp sân bay Chu Lai để đón 5 triệu hành khách một năm ...",
        "url": "http://www.saigontel.vn/vi/tin-tuc/tin-tuc/1136-nang-cap-san-bay-chu-lai-de-don-5-trieu-hanh-khach-mot-nam.html",
        "ngay_crawl": "2025-09-12 17:01:01"
    },
    {
        "id": 2,
        "title": "115.000 tỷ đồng đổ vào hạ tầng giao thông, BĐS khu Nam Sài Gòn hưởng lợi lớn, ngày càng sôi động ...",
        "url": "http://www.saigontel.vn/vi/tin-tuc/tin-tuc/1135-115000-ty-dong-do-vao-ha-tang-giao-thong-bds-khu-nam-sai-gon-huong-loi-lon-ngay-cang-soi-dong.html",
        "ngay_crawl": "2025-09-12 17:01:01"
    },
    {
        "id": 3,
        "title": "(Biznews) Kéo ông lớn Mỹ đầu tư vào Việt Nam ...",
        "url": "http://www.saigontel.vn/vi/tin-tuc/tin-tuc/1134-keo-ong-lon-my-dau-tu-vao-viet-nam.html",
        "ngay_crawl": "2025-09-12 17:01:01"
    },
    {
        "id": 4,
        "title": "Ôtô nhập khẩu sắp được 'cởi trói' nhiều quy định ...",
        "url": "http://www.saigontel.vn/vi/tin-tuc/tin-tuc/1131-oto-nhap-khau-sap-duoc-coi-troi-nhieu-quy-dinh.html",
        "ngay_crawl": "2025-09-12 17:01:01"
    },
    {
        "id": 5,
        "title": "Doanh nghiệp Việt phải 'chuyển mình' để tận dụng EVFTA ...",
        "url": "http://www.saigontel.vn/vi/tin-tuc/tin-tuc/1130-doanh-nghiep-viet-phai-chuyen-minh-de-tan-dung-evfta.html",
        "ngay_crawl": "2025-09-12 17:01:01"
    },
    {
        "id": 6,
        "title": "Bloomberg: Mạng 5G Viettel không dùng thiết bị Huawei ...",
        "url": "http://www.saigontel.vn/vi/tin-tuc/tin-tuc/1129-bloomberg-mang-5g-viettel-khong-dung-thiet-bi-huawei.html",
        "ngay_crawl": "2025-09-12 17:01:01"
    },
    {
        "id": 7,
        "title": "Ngân hàng Nhà nước \"tung\" tiền hỗ trợ thị trường ...",
        "url": "http://www.saigontel.vn/vi/tin-tuc/tin-tuc/1128-ngan-hang-nha-nuoc-tung-tien-ho-tro-thi-truong.html",
        "ngay_crawl": "2025-09-12 17:01:01"
    },
    {
        "id": 8,
        "title": "Quỹ đầu tư 35 tỷ USD gọi Việt Nam là “điểm đến rất thú vị” ...",
        "url": "http://www.saigontel.vn/vi/tin-tuc/tin-tuc/1127-quy-dau-tu-35-ty-usd-goi-viet-nam-la-diem-den-rat-thu-vi.html",
        "ngay_crawl": "2025-09-12 17:01:01"
    },
    {
        "id": 9,
        "title": "Việt Nam thu về 1,17 tỷ USD nhờ xuất khẩu xăng dầu ...",
        "url": "http://www.saigontel.vn/vi/tin-tuc/tin-tuc/1126-viet-nam-thu-ve-117-ty-usd-nho-xuat-khau-xang-dau.html",
        "ngay_crawl": "2025-09-12 17:01:01"
    }
]