[
    {
        "id": 1,
        "title": "Hà Nội chính thức áp dụng quy định mới về hệ số điều chỉnh giá đất từ ngày 12/3 ...",
        "url": "http://www.saigontel.vn/vi/tin-tuc/tin-tuc/1731-ha-noi-chinh-thuc-ap-dung-quy-dinh-moi-ve-he-so-dieu-chinh-gia-dat-tu-ngay-123.html",
        "ngay_crawl": "2025-09-12 17:00:06"
    },
    {
        "id": 2,
        "title": "Thế giới chi gần 124 tỷ USD cho đô thị thông minh trong năm 2020 ...",
        "url": "http://www.saigontel.vn/vi/tin-tuc/tin-tuc/1730-the-gioi-chi-gan-124-ty-usd-cho-do-thi-thong-minh-trong-nam-2020.html",
        "ngay_crawl": "2025-09-12 17:00:06"
    },
    {
        "id": 3,
        "title": "Quy hoạch Đà Nẵng là trung tâm khởi nghiệp, đổi mới sáng tạo… ...",
        "url": "http://www.saigontel.vn/vi/tin-tuc/tin-tuc/1729-quy-hoach-da-nang-la-trung-tam-khoi-nghiep-doi-moi-sang-tao.html",
        "ngay_crawl": "2025-09-12 17:00:06"
    },
    {
        "id": 4,
        "title": "Xuất nhập khẩu đầu năm tăng nhẹ ...",
        "url": "http://www.saigontel.vn/vi/tin-tuc/tin-tuc/1728-xuat-nhap-khau-dau-nam-tang-nhe.html",
        "ngay_crawl": "2025-09-12 17:00:06"
    },
    {
        "id": 5,
        "title": "Hiệu ứng nhân rộng của RCEP đối với dòng chảy thương mại ASEAN ...",
        "url": "http://www.saigontel.vn/vi/tin-tuc/tin-tuc/1727-hieu-ung-nhan-rong-cua-rcep-doi-voi-dong-chay-thuong-mai-asean.html",
        "ngay_crawl": "2025-09-12 17:00:06"
    },
    {
        "id": 6,
        "title": "Xuất khẩu điện thoại, máy tính, giày dép... sang Mỹ tăng khủng ...",
        "url": "http://www.saigontel.vn/vi/tin-tuc/tin-tuc/1726-xuat-khau-dien-thoai-may-tinh-giay-dep-sang-my-tang-khung.html",
        "ngay_crawl": "2025-09-12 17:00:06"
    },
    {
        "id": 7,
        "title": "[Infographics] Mục tiêu xuất khẩu gạo năm 2020 đạt hơn 6 triệu tấn ...",
        "url": "http://www.saigontel.vn/vi/tin-tuc/tin-tuc/1725-infographics-muc-tieu-xuat-khau-gao-nam-2020-dat-hon-6-trieu-tan.html",
        "ngay_crawl": "2025-09-12 17:00:06"
    },
    {
        "id": 8,
        "title": "Gần 4.600 ô tô nhập khẩu trong nửa đầu tháng 3 ...",
        "url": "http://www.saigontel.vn/vi/tin-tuc/tin-tuc/1724-gan-4600-o-to-nhap-khau-trong-nua-dau-thang-3.html",
        "ngay_crawl": "2025-09-12 17:00:06"
    },
    {
        "id": 9,
        "title": "4 loại hình bất động sản sẽ tăng trưởng đột biến giúp nhà đầu tư \"hái ra tiền\" trong mùa d ...",
        "url": "http://www.saigontel.vn/vi/tin-tuc/tin-tuc/1723-4-loai-hinh-bat-dong-san-se-tang-truong-dot-bien-giup-nha-dau-tu-hai-ra-tien-trong-mua-dich.html",
        "ngay_crawl": "2025-09-12 17:00:06"
    }
]